PROJ/PD1/main-mem/main-memrv32ui-p-lhu.v
`define FILE_PATH "../../rv32-benchmarks-master/individual-instructions/rv32ui-p-lhu.x"
`define FILE_LINES 179
`define VCD "main-mem-rv32ui-p-lhu.vcd"

`define MEM_DEPTH_BYTES 'h0100000

`define READ 0
`define WRITE 1

`define HALF_CYCLE 10

/*========================================================================================*/

// main memory component
module mainmem (
	input clock,
	input [31:0] address,
	input [31:0] data_in,
	output [31:0] data_out,
	input read_write); 

    parameter STARTING_ADDR = 'h01000000;

	wire read_write;
	wire [31:0] address;
	wire [31:0] data_in;
	reg [31:0] data_out;

	reg [7:0] mem[0:`MEM_DEPTH_BYTES - 1];

    // read mode
	always @(clock or address or read_write) begin
		if (read_write == `READ)
			data_out <= {
				mem[address - STARTING_ADDR + 3],
				mem[address - STARTING_ADDR + 2],
				mem[address - STARTING_ADDR + 1],
				mem[address - STARTING_ADDR]
			};
		else
			data_out <= 32'hXXXXXXXX;
	end

	// write mode
    always @(posedge clock) begin
        if (read_write == `WRITE) begin
            mem[address - STARTING_ADDR + 3] <= data_in[31:24];
            mem[address - STARTING_ADDR + 2] <= data_in[23:16];
            mem[address - STARTING_ADDR + 1] <= data_in[15:8];
            mem[address - STARTING_ADDR] <= data_in[7:0];
        end
	end

	// testbench
	reg [31:0] tmp_mem[0:(`MEM_DEPTH_BYTES / 4) - 1];
	integer i;
    
    initial begin
        $readmemh(`FILE_PATH, tmp_mem);

		// copy to mem
		i = 0;
		while (tmp_mem[i] !== 32'hX) begin
			mem[(4 * i) + 3] <= tmp_mem[i][31:24];
            mem[(4 * i) + 2] <= tmp_mem[i][23:16];
            mem[(4 * i) + 1] <= tmp_mem[i][15:8];
            mem[(4 * i)] <= tmp_mem[i][7:0];
			i += 1;
		end
    end
endmodule // mainmem

/*========================================================================================*/

// testbench

module dut;
    parameter STARTING_ADDR = 'h01000000;
	
	reg clock = 0;
	reg [31:0] pc;
	reg read_write = 0;
	reg [31:0] data_in;
    wire [31:0] data_out;

    initial begin
        $dumpfile(`VCD);
        $dumpvars(0, memory);

		#(`HALF_CYCLE / 2) pc = STARTING_ADDR;

		#(`FILE_LINES * 4 * `HALF_CYCLE) $finish;
    end
	
	mainmem memory(
		.clock(clock),
		.address(pc),
		.data_in(data_in),
		.data_out(data_out),
		.read_write(read_write));
	
	always @(posedge clock) begin
        $display("time=%t, address=%8h, data_out=%8h", $time, pc, data_out);
        #(`HALF_CYCLE / 2)  pc <= pc + 4;
	end
	
	always begin                 
		#`HALF_CYCLE clock = ~clock;
	end
endmodule

PROJ/PD1/main-mem/main-mem-CheckVowel.vcd
$date
	Mon May 25 16:18:18 2020
$end
$version
	Icarus Verilog
$end
$timescale
	1s
$end
$scope module dut $end
$scope module memory $end
$var wire 32 ! address [31:0] $end
$var wire 1 " clock $end
$var wire 32 # data_in [31:0] $end
$var wire 1 $ read_write $end
$var reg 32 % data_out [31:0] $end
$var integer 32 & i [31:0] $end
$upscope $end
$upscope $end
$enddefinitions $end
#0
$dumpvars
b1111111 &
bx %
0$
bx #
0"
bx !
$end
#5
b11111101000000010000000100010011 %
b1000000000000000000000000 !
#10
1"
#15
b10000100010010011000100011 %
b1000000000000000000000100 !
#20
0"
#30
1"
#35
b10010111000100011 %
b1000000000000000000001000 !
#40
0"
#50
1"
#55
b10010110000100011 %
b1000000000000000000001100 !
#60
0"
#70
1"
#75
b1000000000000011110110111 %
b1000000000000000000010000 !
#80
0"
#90
1"
#95
b11110100001111010011000000011 %
b1000000000000000000010100 !
#100
0"
#110
1"
#115
b11110100001111000011100010011 %
b1000000000000000000011000 !
#120
0"
#130
1"
#135
b10001110010011010000011 %
b1000000000000000000011100 !
#140
0"
#150
1"
#155
b11110100001111000011100010011 %
b1000000000000000000100000 !
#160
0"
#170
1"
#175
b100001110010011100000011 %
b1000000000000000000100100 !
#180
0"
#190
1"
#195
b110000010010001000100011 %
b1000000000000000000101000 !
#200
0"
#210
1"
#215
b110100010010010000100011 %
b1000000000000000000101100 !
#220
0"
#230
1"
#235
b111000010010011000100011 %
b1000000000000000000110000 !
#240
0"
#250
1"
#255
b11110100001111000011110010011 %
b1000000000000000000110100 !
#260
0"
#270
1"
#275
b110001111100011110000011 %
b1000000000000000000111000 !
#280
0"
#290
1"
#295
b111100010000100000100011 %
b1000000000000000000111100 !
#300
0"
#310
1"
#315
b10000100010100011 %
b1000000000000000001000000 !
#320
0"
#330
1"
#335
b10000100100100011 %
b1000000000000000001000100 !
#340
0"
#350
1"
#355
b10000100110100011 %
b1000000000000000001001000 !
#360
0"
#370
1"
#375
b10000101000100011 %
b1000000000000000001001100 !
#380
0"
#390
1"
#395
b10000101010100011 %
b1000000000000000001010000 !
#400
0"
#410
1"
#415
b10000101100100011 %
b1000000000000000001010100 !
#420
0"
#430
1"
#435
b10000101110100011 %
b1000000000000000001011000 !
#440
0"
#450
1"
#455
b10010111000100011 %
b1000000000000000001011100 !
#460
0"
#470
1"
#475
b10000110000000000000001101111 %
b1000000000000000001100000 !
#480
0"
#490
1"
#495
b1110000010010011110000011 %
b1000000000000000001100100 !
#500
0"
#510
1"
#515
b10000000010000011100010011 %
b1000000000000000001101000 !
#520
0"
#530
1"
#535
b111101110000011110110011 %
b1000000000000000001101100 !
#540
0"
#550
1"
#555
b11111110010001111100011100000011 %
b1000000000000000001110000 !
#560
0"
#570
1"
#575
b110000100000000011110010011 %
b1000000000000000001110100 !
#580
0"
#590
1"
#595
b1100111101110000111001100011 %
b1000000000000000001111000 !
#600
0"
#610
1"
#615
b1110000010010011110000011 %
b1000000000000000001111100 !
#620
0"
#630
1"
#635
b10000000010000011100010011 %
b1000000000000000010000000 !
#640
0"
#650
1"
#655
b111101110000011110110011 %
b1000000000000000010000100 !
#660
0"
#670
1"
#675
b11111110010001111100011100000011 %
b1000000000000000010001000 !
#680
0"
#690
1"
#695
b100000100000000011110010011 %
b1000000000000000010001100 !
#700
0"
#710
1"
#715
b1100111101110000001001100011 %
b1000000000000000010010000 !
#720
0"
#730
1"
#735
b1110000010010011110000011 %
b1000000000000000010010100 !
#740
0"
#750
1"
#755
b10000000010000011100010011 %
b1000000000000000010011000 !
#760
0"
#770
1"
#775
b111101110000011110110011 %
b1000000000000000010011100 !
#780
0"
#790
1"
#795
b11111110010001111100011100000011 %
b1000000000000000010100000 !
#800
0"
#810
1"
#815
b110010100000000011110010011 %
b1000000000000000010100100 !
#820
0"
#830
1"
#835
b1010111101110000011001100011 %
b1000000000000000010101000 !
#840
0"
#850
1"
#855
b1110000010010011110000011 %
b1000000000000000010101100 !
#860
0"
#870
1"
#875
b10000000010000011100010011 %
b1000000000000000010110000 !
#880
0"
#890
1"
#895
b111101110000011110110011 %
b1000000000000000010110100 !
#900
0"
#910
1"
#915
b11111110010001111100011100000011 %
b1000000000000000010111000 !
#920
0"
#930
1"
#935
b100010100000000011110010011 %
b1000000000000000010111100 !
#940
0"
#950
1"
#955
b1000111101110000101001100011 %
b1000000000000000011000000 !
#960
0"
#970
1"
#975
b1110000010010011110000011 %
b1000000000000000011000100 !
#980
0"
#990
1"
#995
b10000000010000011100010011 %
b1000000000000000011001000 !
#1000
0"
#1010
1"
#1015
b111101110000011110110011 %
b1000000000000000011001100 !
#1020
0"
#1030
1"
#1035
b11111110010001111100011100000011 %
b1000000000000000011010000 !
#1040
0"
#1050
1"
#1055
b110100100000000011110010011 %
b1000000000000000011010100 !
#1060
0"
#1070
1"
#1075
b110111101110000111001100011 %
b1000000000000000011011000 !
#1080
0"
#1090
1"
#1095
b1110000010010011110000011 %
b1000000000000000011011100 !
#1100
0"
#1110
1"
#1115
b10000000010000011100010011 %
b1000000000000000011100000 !
#1120
0"
#1130
1"
#1135
b111101110000011110110011 %
b1000000000000000011100100 !
#1140
0"
#1150
1"
#1155
b11111110010001111100011100000011 %
b1000000000000000011101000 !
#1160
0"
#1170
1"
#1175
b100100100000000011110010011 %
b1000000000000000011101100 !
#1180
0"
#1190
1"
#1195
b110111101110000001001100011 %
b1000000000000000011110000 !
#1200
0"
#1210
1"
#1215
b1110000010010011110000011 %
b1000000000000000011110100 !
#1220
0"
#1230
1"
#1235
b10000000010000011100010011 %
b1000000000000000011111000 !
#1240
0"
#1250
1"
#1255
b111101110000011110110011 %
b1000000000000000011111100 !
#1260
0"
#1270
1"
#1275
b11111110010001111100011100000011 %
b1000000000000000100000000 !
#1280
0"
#1290
1"
#1295
b110111100000000011110010011 %
b1000000000000000100000100 !
#1300
0"
#1310
1"
#1315
b100111101110000011001100011 %
b1000000000000000100001000 !
#1320
0"
#1330
1"
#1335
b1110000010010011110000011 %
b1000000000000000100001100 !
#1340
0"
#1350
1"
#1355
b10000000010000011100010011 %
b1000000000000000100010000 !
#1360
0"
#1370
1"
#1375
b111101110000011110110011 %
b1000000000000000100010100 !
#1380
0"
#1390
1"
#1395
b11111110010001111100011100000011 %
b1000000000000000100011000 !
#1400
0"
#1410
1"
#1415
b100111100000000011110010011 %
b1000000000000000100011100 !
#1420
0"
#1430
1"
#1435
b10111101110000101001100011 %
b1000000000000000100100000 !
#1440
0"
#1450
1"
#1455
b1110000010010011110000011 %
b1000000000000000100100100 !
#1460
0"
#1470
1"
#1475
b10000000010000011100010011 %
b1000000000000000100101000 !
#1480
0"
#1490
1"
#1495
b111101110000011110110011 %
b1000000000000000100101100 !
#1500
0"
#1510
1"
#1515
b11111110010001111100011100000011 %
b1000000000000000100110000 !
#1520
0"
#1530
1"
#1535
b111010100000000011110010011 %
b1000000000000000100110100 !
#1540
0"
#1550
1"
#1555
b111101110000111001100011 %
b1000000000000000100111000 !
#1560
0"
#1570
1"
#1575
b1110000010010011110000011 %
b1000000000000000100111100 !
#1580
0"
#1590
1"
#1595
b10000000010000011100010011 %
b1000000000000000101000000 !
#1600
0"
#1610
1"
#1615
b111101110000011110110011 %
b1000000000000000101000100 !
#1620
0"
#1630
1"
#1635
b11111110010001111100011100000011 %
b1000000000000000101001000 !
#1640
0"
#1650
1"
#1655
b101010100000000011110010011 %
b1000000000000000101001100 !
#1660
0"
#1670
1"
#1675
b111101110001100001100011 %
b1000000000000000101010000 !
#1680
0"
#1690
1"
#1695
b1100000010010011110000011 %
b1000000000000000101010100 !
#1700
0"
#1710
1"
#1715
b101111000011110010011 %
b1000000000000000101011000 !
#1720
0"
#1730
1"
#1735
b111100010010110000100011 %
b1000000000000000101011100 !
#1740
0"
#1750
1"
#1755
b1110000010010011110000011 %
b1000000000000000101100000 !
#1760
0"
#1770
1"
#1775
b101111000011110010011 %
b1000000000000000101100100 !
#1780
0"
#1790
1"
#1795
b111100010010111000100011 %
b1000000000000000101101000 !
#1800
0"
#1810
1"
#1815
b1110000010010011100000011 %
b1000000000000000101101100 !
#1820
0"
#1830
1"
#1835
b1001100000000011110010011 %
b1000000000000000101110000 !
#1840
0"
#1850
1"
#1855
b11101110111001111101100011100011 %
b1000000000000000101110100 !
#1860
0"
#1870
1"
#1875
b1100000010010010100000011 %
b1000000000000000101111000 !
#1880
0"
#1890
1"
#1895
b1100000000000000011101111 %
b1000000000000000101111100 !
#1900
0"
#1910
1"
#1915
b1010000011110010011 %
b1000000000000000110000000 !
#1920
0"
#1930
1"
#1935
b1111000010100010011 %
b1000000000000000110000100 !
#1940
0"
#1950
1"
#1955
b10110000010010000010000011 %
b1000000000000000110001000 !
#1960
0"
#1970
1"
#1975
b11000000010000000100010011 %
b1000000000000000110001100 !
#1980
0"
#1990
1"
#1995
b1000000001100111 %
b1000000000000000110010000 !
#2000
0"
#2010
1"
#2015
b11111110000000010000000100010011 %
b1000000000000000110010100 !
#2020
0"
#2030
1"
#2035
b100010010111000100011 %
b1000000000000000110011000 !
#2040
0"
#2050
1"
#2055
b101000010010011000100011 %
b1000000000000000110011100 !
#2060
0"
#2070
1"
#2075
b110000010010011100000011 %
b1000000000000000110100000 !
#2080
0"
#2090
1"
#2095
b1100000000011110010011 %
b1000000000000000110100100 !
#2100
0"
#2110
1"
#2115
b111101110001100001100011 %
b1000000000000000110101000 !
#2120
0"
#2130
1"
#2135
b10010000000000000011101111 %
b1000000000000000110101100 !
#2140
0"
#2150
1"
#2155
b1010000011110010011 %
b1000000000000000110110000 !
#2160
0"
#2170
1"
#2175
b110000000000000001101111 %
b1000000000000000110110100 !
#2180
0"
#2190
1"
#2195
b10010000000000000011101111 %
b1000000000000000110111000 !
#2200
0"
#2210
1"
#2215
b1010000011110010011 %
b1000000000000000110111100 !
#2220
0"
#2230
1"
#2235
b1111000010100010011 %
b1000000000000000111000000 !
#2240
0"
#2250
1"
#2255
b1110000010010000010000011 %
b1000000000000000111000100 !
#2260
0"
#2270
1"
#2275
b10000000010000000100010011 %
b1000000000000000111001000 !
#2280
0"
#2290
1"
#2295
b1000000001100111 %
b1000000000000000111001100 !
#2300
0"
#2310
1"
#2315
b100000000011110010011 %
b1000000000000000111010000 !
#2320
0"
#2330
1"
#2335
b1111000010100010011 %
b1000000000000000111010100 !
#2340
0"
#2350
1"
#2355
b1000000001100111 %
b1000000000000000111011000 !
#2360
0"
#2370
1"
#2375
b11110010011 %
b1000000000000000111011100 !
#2380
0"
#2390
1"
#2395
b1111000010100010011 %
b1000000000000000111100000 !
#2400
0"
#2410
1"
#2415
b1000000001100111 %
b1000000000000000111100100 !
#2420
0"
#2430
1"
#2435
b1100011011001010110100001000011 %
b1000000000000000111101000 !
#2440
0"
#2450
1"
#2455
b1110111011011110101011001101011 %
b1000000000000000111101100 !
#2460
0"
#2470
1"
#2475
b1010001000010110110001100101 %
b1000000000000000111110000 !
#2480
0"
#2490
1"
#2495
b0 %
b1000000000000000111110100 !
#2500
0"
#2510
1"
#2515
b1000000000000000111111000 !
#2520
0"
#2530
1"
#2535
bx %
b1000000000000000111111100 !
#2540
0"
#2550
1"
#2555
b1000000000000001000000000 !
#2560
0"
#2570
1"
#2575
b1000000000000001000000100 !
#2580
0"
#2590
1"
#2595
b1000000000000001000001000 !
#2600
0"
#2610
1"
#2615
b1000000000000001000001100 !
#2620
0"
#2630
1"
#2635
b1000000000000001000010000 !
#2640
0"
#2650
1"
#2655
b1000000000000001000010100 !
#2660
0"
#2670
1"
#2675
b1000000000000001000011000 !
#2680
0"
#2690
1"
#2695
b1000000000000001000011100 !
#2700
0"
#2710
1"
#2715
b1000000000000001000100000 !
#2720
0"
#2730
1"
#2735
b1000000000000001000100100 !
#2740
0"
#2750
1"
#2755
b1000000000000001000101000 !
#2760
0"
#2770
1"
#2775
b1000000000000001000101100 !
#2780
0"
#2790
1"
#2795
b1000000000000001000110000 !
#2800
0"
#2810
1"
#2815
b1000000000000001000110100 !
#2820
0"
#2830
1"
#2835
b1000000000000001000111000 !
#2840
0"
#2850
1"
#2855
b1000000000000001000111100 !
#2860
0"
#2870
1"
#2875
b1000000000000001001000000 !
#2880
0"
#2890
1"
#2895
b1000000000000001001000100 !
#2900
0"
#2910
1"
#2915
b1000000000000001001001000 !
#2920
0"
#2930
1"
#2935
b1000000000000001001001100 !
#2940
0"
#2950
1"
#2955
b1000000000000001001010000 !
#2960
0"
#2970
1"
#2975
b1000000000000001001010100 !
#2980
0"
#2990
1"
#2995
b1000000000000001001011000 !
#3000
0"
#3010
1"
#3015
b1000000000000001001011100 !
#3020
0"
#3030
1"
#3035
b1000000000000001001100000 !
#3040
0"
#3050
1"
#3055
b1000000000000001001100100 !
#3060
0"
#3070
1"
#3075
b1000000000000001001101000 !
#3080
0"
#3090
1"
#3095
b1000000000000001001101100 !
#3100
0"
#3110
1"
#3115
b1000000000000001001110000 !
#3120
0"
#3130
1"
#3135
b1000000000000001001110100 !
#3140
0"
#3150
1"
#3155
b1000000000000001001111000 !
#3160
0"
#3170
1"
#3175
b1000000000000001001111100 !
#3180
0"
#3190
1"
#3195
b1000000000000001010000000 !
#3200
0"
#3210
1"
#3215
b1000000000000001010000100 !
#3220
0"
#3230
1"
#3235
b1000000000000001010001000 !
#3240
0"
#3250
1"
#3255
b1000000000000001010001100 !
#3260
0"
#3270
1"
#3275
b1000000000000001010010000 !
#3280
0"
#3290
1"
#3295
b1000000000000001010010100 !
#3300
0"
#3310
1"
#3315
b1000000000000001010011000 !
#3320
0"
#3330
1"
#3335
b1000000000000001010011100 !
#3340
0"
#3350
1"
#3355
b1000000000000001010100000 !
#3360
0"
#3370
1"
#3375
b1000000000000001010100100 !
#3380
0"
#3390
1"
#3395
b1000000000000001010101000 !
#3400
0"
#3410
1"
#3415
b1000000000000001010101100 !
#3420
0"
#3430
1"
#3435
b1000000000000001010110000 !
#3440
0"
#3450
1"
#3455
b1000000000000001010110100 !
#3460
0"
#3470
1"
#3475
b1000000000000001010111000 !
#3480
0"
#3490
1"
#3495
b1000000000000001010111100 !
#3500
0"
#3510
1"
#3515
b1000000000000001011000000 !
#3520
0"
#3530
1"
#3535
b1000000000000001011000100 !
#3540
0"
#3550
1"
#3555
b1000000000000001011001000 !
#3560
0"
#3570
1"
#3575
b1000000000000001011001100 !
#3580
0"
#3590
1"
#3595
b1000000000000001011010000 !
#3600
0"
#3610
1"
#3615
b1000000000000001011010100 !
#3620
0"
#3630
1"
#3635
b1000000000000001011011000 !
#3640
0"
#3650
1"
#3655
b1000000000000001011011100 !
#3660
0"
#3670
1"
#3675
b1000000000000001011100000 !
#3680
0"
#3690
1"
#3695
b1000000000000001011100100 !
#3700
0"
#3710
1"
#3715
b1000000000000001011101000 !
#3720
0"
#3730
1"
#3735
b1000000000000001011101100 !
#3740
0"
#3750
1"
#3755
b1000000000000001011110000 !
#3760
0"
#3770
1"
#3775
b1000000000000001011110100 !
#3780
0"
#3790
1"
#3795
b1000000000000001011111000 !
#3800
0"
#3810
1"
#3815
b1000000000000001011111100 !
#3820
0"
#3830
1"
#3835
b1000000000000001100000000 !
#3840
0"
#3850
1"
#3855
b1000000000000001100000100 !
#3860
0"
#3870
1"
#3875
b1000000000000001100001000 !
#3880
0"
#3890
1"
#3895
b1000000000000001100001100 !
#3900
0"
#3910
1"
#3915
b1000000000000001100010000 !
#3920
0"
#3930
1"
#3935
b1000000000000001100010100 !
#3940
0"
#3950
1"
#3955
b1000000000000001100011000 !
#3960
0"
#3970
1"
#3975
b1000000000000001100011100 !
#3980
0"
#3990
1"
#3995
b1000000000000001100100000 !
#4000
0"
#4010
1"
#4015
b1000000000000001100100100 !
#4020
0"
#4030
1"
#4035
b1000000000000001100101000 !
#4040
0"
#4050
1"
#4055
b1000000000000001100101100 !
#4060
0"
#4070
1"
#4075
b1000000000000001100110000 !
#4080
0"
#4090
1"
#4095
b1000000000000001100110100 !
#4100
0"
#4110
1"
#4115
b1000000000000001100111000 !
#4120
0"
#4130
1"
#4135
b1000000000000001100111100 !
#4140
0"
#4150
1"
#4155
b1000000000000001101000000 !
#4160
0"
#4170
1"
#4175
b1000000000000001101000100 !
#4180
0"
#4190
1"
#4195
b1000000000000001101001000 !
#4200
0"
#4210
1"
#4215
b1000000000000001101001100 !
#4220
0"
#4230
1"
#4235
b1000000000000001101010000 !
#4240
0"
#4250
1"
#4255
b1000000000000001101010100 !
#4260
0"
#4270
1"
#4275
b1000000000000001101011000 !
#4280
0"
#4290
1"
#4295
b1000000000000001101011100 !
#4300
0"
#4310
1"
#4315
b1000000000000001101100000 !
#4320
0"
#4330
1"
#4335
b1000000000000001101100100 !
#4340
0"
#4350
1"
#4355
b1000000000000001101101000 !
#4360
0"
#4370
1"
#4375
b1000000000000001101101100 !
#4380
0"
#4390
1"
#4395
b1000000000000001101110000 !
#4400
0"
#4410
1"
#4415
b1000000000000001101110100 !
#4420
0"
#4430
1"
#4435
b1000000000000001101111000 !
#4440
0"
#4450
1"
#4455
b1000000000000001101111100 !
#4460
0"
#4470
1"
#4475
b1000000000000001110000000 !
#4480
0"
#4490
1"
#4495
b1000000000000001110000100 !
#4500
0"
#4510
1"
#4515
b1000000000000001110001000 !
#4520
0"
#4530
1"
#4535
b1000000000000001110001100 !
#4540
0"
#4550
1"
#4555
b1000000000000001110010000 !
#4560
0"
#4570
1"
#4575
b1000000000000001110010100 !
#4580
0"
#4590
1"
#4595
b1000000000000001110011000 !
#4600
0"
#4610
1"
#4615
b1000000000000001110011100 !
#4620
0"
#4630
1"
#4635
b1000000000000001110100000 !
#4640
0"
#4650
1"
#4655
b1000000000000001110100100 !
#4660
0"
#4670
1"
#4675
b1000000000000001110101000 !
#4680
0"
#4690
1"
#4695
b1000000000000001110101100 !
#4700
0"
#4710
1"
#4715
b1000000000000001110110000 !
#4720
0"
#4730
1"
#4735
b1000000000000001110110100 !
#4740
0"
#4750
1"
#4755
b1000000000000001110111000 !
#4760
0"
#4770
1"
#4775
b1000000000000001110111100 !
#4780
0"
#4790
1"
#4795
b1000000000000001111000000 !
#4800
0"
#4810
1"
#4815
b1000000000000001111000100 !
#4820
0"
#4830
1"
#4835
b1000000000000001111001000 !
#4840
0"
#4850
1"
#4855
b1000000000000001111001100 !
#4860
0"
#4870
1"
#4875
b1000000000000001111010000 !
#4880
0"
#4890
1"
#4895
b1000000000000001111010100 !
#4900
0"
#4910
1"
#4915
b1000000000000001111011000 !
#4920
0"
#4930
1"
#4935
b1000000000000001111011100 !
#4940
0"
#4950
1"
#4955
b1000000000000001111100000 !
#4960
0"
#4970
1"
#4975
b1000000000000001111100100 !
#4980
0"
#4990
1"
#4995
b1000000000000001111101000 !
#5000
0"
#5010
1"
#5015
b1000000000000001111101100 !
#5020
0"
#5030
1"
#5035
b1000000000000001111110000 !
#5040
0"
#5050
1"
#5055
b1000000000000001111110100 !
#5060
0"
#5070
1"
#5075
b1000000000000001111111000 !
