PROJ/PD1/main-mem/main-memrv32ui-p-lhu.v
`define FILE_PATH "../../rv32-benchmarks-master/individual-instructions/rv32ui-p-lhu.x"
`define FILE_LINES 179
`define VCD "main-mem-rv32ui-p-lhu.vcd"

`define MEM_DEPTH_BYTES 'h0100000

`define READ 0
`define WRITE 1

`define HALF_CYCLE 10

/*========================================================================================*/

// main memory component
module mainmem (
	input clock,
	input [31:0] address,
	input [31:0] data_in,
	output [31:0] data_out,
	input read_write); 

    parameter STARTING_ADDR = 'h01000000;

	wire read_write;
	wire [31:0] address;
	wire [31:0] data_in;
	reg [31:0] data_out;

	reg [7:0] mem[0:`MEM_DEPTH_BYTES - 1];

    // read mode
	always @(clock or address or read_write) begin
		if (read_write == `READ)
			data_out <= {
				mem[address - STARTING_ADDR + 3],
				mem[address - STARTING_ADDR + 2],
				mem[address - STARTING_ADDR + 1],
				mem[address - STARTING_ADDR]
			};
		else
			data_out <= 32'hXXXXXXXX;
	end

	// write mode
    always @(posedge clock) begin
        if (read_write == `WRITE) begin
            mem[address - STARTING_ADDR + 3] <= data_in[31:24];
            mem[address - STARTING_ADDR + 2] <= data_in[23:16];
            mem[address - STARTING_ADDR + 1] <= data_in[15:8];
            mem[address - STARTING_ADDR] <= data_in[7:0];
        end
	end

	// testbench
	reg [31:0] tmp_mem[0:(`MEM_DEPTH_BYTES / 4) - 1];
	integer i;
    
    initial begin
        $readmemh(`FILE_PATH, tmp_mem);

		// copy to mem
		i = 0;
		while (tmp_mem[i] !== 32'hX) begin
			mem[(4 * i) + 3] <= tmp_mem[i][31:24];
            mem[(4 * i) + 2] <= tmp_mem[i][23:16];
            mem[(4 * i) + 1] <= tmp_mem[i][15:8];
            mem[(4 * i)] <= tmp_mem[i][7:0];
			i += 1;
		end
    end
endmodule // mainmem

/*========================================================================================*/

// testbench

module dut;
    parameter STARTING_ADDR = 'h01000000;
	
	reg clock = 0;
	reg [31:0] pc;
	reg read_write = 0;
	reg [31:0] data_in;
    wire [31:0] data_out;

    initial begin
        $dumpfile(`VCD);
        $dumpvars(0, memory);

		#(`HALF_CYCLE / 2) pc = STARTING_ADDR;

		#(`FILE_LINES * 4 * `HALF_CYCLE) $finish;
    end
	
	mainmem memory(
		.clock(clock),
		.address(pc),
		.data_in(data_in),
		.data_out(data_out),
		.read_write(read_write));
	
	always @(posedge clock) begin
        $display("time=%t, address=%8h, data_out=%8h", $time, pc, data_out);
        #(`HALF_CYCLE / 2)  pc <= pc + 4;
	end
	
	always begin                 
		#`HALF_CYCLE clock = ~clock;
	end
endmodule

PROJ/PD1/main-mem/main-mem-SimpleAdd.vcd
$date
	Mon May 25 16:18:19 2020
$end
$version
	Icarus Verilog
$end
$timescale
	1s
$end
$scope module dut $end
$scope module memory $end
$var wire 32 ! address [31:0] $end
$var wire 1 " clock $end
$var wire 32 # data_in [31:0] $end
$var wire 1 $ read_write $end
$var reg 32 % data_out [31:0] $end
$var integer 32 & i [31:0] $end
$upscope $end
$upscope $end
$enddefinitions $end
#0
$dumpvars
b100111 &
bx %
0$
bx #
0"
bx !
$end
#5
b11111110000000010000000100010011 %
b1000000000000000000000000 !
#10
1"
#15
b100010010111000100011 %
b1000000000000000000000100 !
#20
0"
#30
1"
#35
b1100000000011110010011 %
b1000000000000000000001000 !
#40
0"
#50
1"
#55
b111100010010011000100011 %
b1000000000000000000001100 !
#60
0"
#70
1"
#75
b1000000000011110010011 %
b1000000000000000000010000 !
#80
0"
#90
1"
#95
b111100010010010000100011 %
b1000000000000000000010100 !
#100
0"
#110
1"
#115
b10010001000100011 %
b1000000000000000000011000 !
#120
0"
#130
1"
#135
b110000010010011100000011 %
b1000000000000000000011100 !
#140
0"
#150
1"
#155
b100000010010011110000011 %
b1000000000000000000100000 !
#160
0"
#170
1"
#175
b111101110000011110110011 %
b1000000000000000000100100 !
#180
0"
#190
1"
#195
b111100010010001000100011 %
b1000000000000000000101000 !
#200
0"
#210
1"
#215
b10000010010010100000011 %
b1000000000000000000101100 !
#220
0"
#230
1"
#235
b1100000000000000011101111 %
b1000000000000000000110000 !
#240
0"
#250
1"
#255
b1010000011110010011 %
b1000000000000000000110100 !
#260
0"
#270
1"
#275
b1111000010100010011 %
b1000000000000000000111000 !
#280
0"
#290
1"
#295
b1110000010010000010000011 %
b1000000000000000000111100 !
#300
0"
#310
1"
#315
b10000000010000000100010011 %
b1000000000000000001000000 !
#320
0"
#330
1"
#335
b1000000001100111 %
b1000000000000000001000100 !
#340
0"
#350
1"
#355
b11111110000000010000000100010011 %
b1000000000000000001001000 !
#360
0"
#370
1"
#375
b100010010111000100011 %
b1000000000000000001001100 !
#380
0"
#390
1"
#395
b101000010010011000100011 %
b1000000000000000001010000 !
#400
0"
#410
1"
#415
b110000010010011100000011 %
b1000000000000000001010100 !
#420
0"
#430
1"
#435
b10100000000011110010011 %
b1000000000000000001011000 !
#440
0"
#450
1"
#455
b111101110001100001100011 %
b1000000000000000001011100 !
#460
0"
#470
1"
#475
b10010000000000000011101111 %
b1000000000000000001100000 !
#480
0"
#490
1"
#495
b1010000011110010011 %
b1000000000000000001100100 !
#500
0"
#510
1"
#515
b110000000000000001101111 %
b1000000000000000001101000 !
#520
0"
#530
1"
#535
b10010000000000000011101111 %
b1000000000000000001101100 !
#540
0"
#550
1"
#555
b1010000011110010011 %
b1000000000000000001110000 !
#560
0"
#570
1"
#575
b1111000010100010011 %
b1000000000000000001110100 !
#580
0"
#590
1"
#595
b1110000010010000010000011 %
b1000000000000000001111000 !
#600
0"
#610
1"
#615
b10000000010000000100010011 %
b1000000000000000001111100 !
#620
0"
#630
1"
#635
b1000000001100111 %
b1000000000000000010000000 !
#640
0"
#650
1"
#655
b100000000011110010011 %
b1000000000000000010000100 !
#660
0"
#670
1"
#675
b1111000010100010011 %
b1000000000000000010001000 !
#680
0"
#690
1"
#695
b1000000001100111 %
b1000000000000000010001100 !
#700
0"
#710
1"
#715
b11110010011 %
b1000000000000000010010000 !
#720
0"
#730
1"
#735
b1111000010100010011 %
b1000000000000000010010100 !
#740
0"
#750
1"
#755
b1000000001100111 %
b1000000000000000010011000 !
#760
0"
#770
1"
#775
bx %
b1000000000000000010011100 !
#780
0"
#790
1"
#795
b1000000000000000010100000 !
#800
0"
#810
1"
#815
b1000000000000000010100100 !
#820
0"
#830
1"
#835
b1000000000000000010101000 !
#840
0"
#850
1"
#855
b1000000000000000010101100 !
#860
0"
#870
1"
#875
b1000000000000000010110000 !
#880
0"
#890
1"
#895
b1000000000000000010110100 !
#900
0"
#910
1"
#915
b1000000000000000010111000 !
#920
0"
#930
1"
#935
b1000000000000000010111100 !
#940
0"
#950
1"
#955
b1000000000000000011000000 !
#960
0"
#970
1"
#975
b1000000000000000011000100 !
#980
0"
#990
1"
#995
b1000000000000000011001000 !
#1000
0"
#1010
1"
#1015
b1000000000000000011001100 !
#1020
0"
#1030
1"
#1035
b1000000000000000011010000 !
#1040
0"
#1050
1"
#1055
b1000000000000000011010100 !
#1060
0"
#1070
1"
#1075
b1000000000000000011011000 !
#1080
0"
#1090
1"
#1095
b1000000000000000011011100 !
#1100
0"
#1110
1"
#1115
b1000000000000000011100000 !
#1120
0"
#1130
1"
#1135
b1000000000000000011100100 !
#1140
0"
#1150
1"
#1155
b1000000000000000011101000 !
#1160
0"
#1170
1"
#1175
b1000000000000000011101100 !
#1180
0"
#1190
1"
#1195
b1000000000000000011110000 !
#1200
0"
#1210
1"
#1215
b1000000000000000011110100 !
#1220
0"
#1230
1"
#1235
b1000000000000000011111000 !
#1240
0"
#1250
1"
#1255
b1000000000000000011111100 !
#1260
0"
#1270
1"
#1275
b1000000000000000100000000 !
#1280
0"
#1290
1"
#1295
b1000000000000000100000100 !
#1300
0"
#1310
1"
#1315
b1000000000000000100001000 !
#1320
0"
#1330
1"
#1335
b1000000000000000100001100 !
#1340
0"
#1350
1"
#1355
b1000000000000000100010000 !
#1360
0"
#1370
1"
#1375
b1000000000000000100010100 !
#1380
0"
#1390
1"
#1395
b1000000000000000100011000 !
#1400
0"
#1410
1"
#1415
b1000000000000000100011100 !
#1420
0"
#1430
1"
#1435
b1000000000000000100100000 !
#1440
0"
#1450
1"
#1455
b1000000000000000100100100 !
#1460
0"
#1470
1"
#1475
b1000000000000000100101000 !
#1480
0"
#1490
1"
#1495
b1000000000000000100101100 !
#1500
0"
#1510
1"
#1515
b1000000000000000100110000 !
#1520
0"
#1530
1"
#1535
b1000000000000000100110100 !
#1540
0"
#1550
1"
#1555
b1000000000000000100111000 !
