PROJ/PD1/main-mem/main-memrv32ui-p-lhu.v
`define FILE_PATH "../../rv32-benchmarks-master/individual-instructions/rv32ui-p-lhu.x"
`define FILE_LINES 179
`define VCD "main-mem-rv32ui-p-lhu.vcd"

`define MEM_DEPTH_BYTES 'h0100000

`define READ 0
`define WRITE 1

`define HALF_CYCLE 10

/*========================================================================================*/

// main memory component
module mainmem (
	input clock,
	input [31:0] address,
	input [31:0] data_in,
	output [31:0] data_out,
	input read_write); 

    parameter STARTING_ADDR = 'h01000000;

	wire read_write;
	wire [31:0] address;
	wire [31:0] data_in;
	reg [31:0] data_out;

	reg [7:0] mem[0:`MEM_DEPTH_BYTES - 1];

    // read mode
	always @(clock or address or read_write) begin
		if (read_write == `READ)
			data_out <= {
				mem[address - STARTING_ADDR + 3],
				mem[address - STARTING_ADDR + 2],
				mem[address - STARTING_ADDR + 1],
				mem[address - STARTING_ADDR]
			};
		else
			data_out <= 32'hXXXXXXXX;
	end

	// write mode
    always @(posedge clock) begin
        if (read_write == `WRITE) begin
            mem[address - STARTING_ADDR + 3] <= data_in[31:24];
            mem[address - STARTING_ADDR + 2] <= data_in[23:16];
            mem[address - STARTING_ADDR + 1] <= data_in[15:8];
            mem[address - STARTING_ADDR] <= data_in[7:0];
        end
	end

	// testbench
	reg [31:0] tmp_mem[0:(`MEM_DEPTH_BYTES / 4) - 1];
	integer i;
    
    initial begin
        $readmemh(`FILE_PATH, tmp_mem);

		// copy to mem
		i = 0;
		while (tmp_mem[i] !== 32'hX) begin
			mem[(4 * i) + 3] <= tmp_mem[i][31:24];
            mem[(4 * i) + 2] <= tmp_mem[i][23:16];
            mem[(4 * i) + 1] <= tmp_mem[i][15:8];
            mem[(4 * i)] <= tmp_mem[i][7:0];
			i += 1;
		end
    end
endmodule // mainmem

/*========================================================================================*/

// testbench

module dut;
    parameter STARTING_ADDR = 'h01000000;
	
	reg clock = 0;
	reg [31:0] pc;
	reg read_write = 0;
	reg [31:0] data_in;
    wire [31:0] data_out;

    initial begin
        $dumpfile(`VCD);
        $dumpvars(0, memory);

		#(`HALF_CYCLE / 2) pc = STARTING_ADDR;

		#(`FILE_LINES * 4 * `HALF_CYCLE) $finish;
    end
	
	mainmem memory(
		.clock(clock),
		.address(pc),
		.data_in(data_in),
		.data_out(data_out),
		.read_write(read_write));
	
	always @(posedge clock) begin
        $display("time=%t, address=%8h, data_out=%8h", $time, pc, data_out);
        #(`HALF_CYCLE / 2)  pc <= pc + 4;
	end
	
	always begin                 
		#`HALF_CYCLE clock = ~clock;
	end
endmodule

PROJ/PD1/main-mem/main-mem-rv32ui-p-slti.vcd
$date
	Mon May 25 16:18:30 2020
$end
$version
	Icarus Verilog
$end
$timescale
	1s
$end
$scope module dut $end
$scope module memory $end
$var wire 32 ! address [31:0] $end
$var wire 1 " clock $end
$var wire 32 # data_in [31:0] $end
$var wire 1 $ read_write $end
$var reg 32 % data_out [31:0] $end
$var integer 32 & i [31:0] $end
$upscope $end
$upscope $end
$enddefinitions $end
#0
$dumpvars
b11010101 &
bx %
0$
bx #
0"
bx !
$end
#5
b10010011 %
b1000000000000000000000000 !
#10
1"
#15
b1010111100010011 %
b1000000000000000000000100 !
#20
0"
#30
1"
#35
b111010010011 %
b1000000000000000000001000 !
#40
0"
#50
1"
#55
b1000000000000110010011 %
b1000000000000000000001100 !
#60
0"
#70
1"
#75
b100111110111110001001001100011 %
b1000000000000000000010000 !
#80
0"
#90
1"
#95
b100000000000010010011 %
b1000000000000000000010100 !
#100
0"
#110
1"
#115
b100001010111100010011 %
b1000000000000000000011000 !
#120
0"
#130
1"
#135
b111010010011 %
b1000000000000000000011100 !
#140
0"
#150
1"
#155
b1100000000000110010011 %
b1000000000000000000100000 !
#160
0"
#170
1"
#175
b100101110111110001100001100011 %
b1000000000000000000100100 !
#180
0"
#190
1"
#195
b1100000000000010010011 %
b1000000000000000000101000 !
#200
0"
#210
1"
#215
b11100001010111100010011 %
b1000000000000000000101100 !
#220
0"
#230
1"
#235
b100000000111010010011 %
b1000000000000000000110000 !
#240
0"
#250
1"
#255
b10000000000000110010011 %
b1000000000000000000110100 !
#260
0"
#270
1"
#275
b100011110111110001111001100011 %
b1000000000000000000111000 !
#280
0"
#290
1"
#295
b11100000000000010010011 %
b1000000000000000000111100 !
#300
0"
#310
1"
#315
b1100001010111100010011 %
b1000000000000000001000000 !
#320
0"
#330
1"
#335
b111010010011 %
b1000000000000000001000100 !
#340
0"
#350
1"
#355
b10100000000000110010011 %
b1000000000000000001001000 !
#360
0"
#370
1"
#375
b100011110111110001010001100011 %
b1000000000000000001001100 !
#380
0"
#390
1"
#395
b10010011 %
b1000000000000000001010000 !
#400
0"
#410
1"
#415
b10000000000000001010111100010011 %
b1000000000000000001010100 !
#420
0"
#430
1"
#435
b111010010011 %
b1000000000000000001011000 !
#440
0"
#450
1"
#455
b11000000000000110010011 %
b1000000000000000001011100 !
#460
0"
#470
1"
#475
b100001110111110001101001100011 %
b1000000000000000001100000 !
#480
0"
#490
1"
#495
b10000000000000000000000010110111 %
b1000000000000000001100100 !
#500
0"
#510
1"
#515
b1010111100010011 %
b1000000000000000001101000 !
#520
0"
#530
1"
#535
b100000000111010010011 %
b1000000000000000001101100 !
#540
0"
#550
1"
#555
b11100000000000110010011 %
b1000000000000000001110000 !
#560
0"
#570
1"
#575
b100001110111110001000001100011 %
b1000000000000000001110100 !
#580
0"
#590
1"
#595
b10000000000000000000000010110111 %
b1000000000000000001111000 !
#600
0"
#610
1"
#615
b10000000000000001010111100010011 %
b1000000000000000001111100 !
#620
0"
#630
1"
#635
b100000000111010010011 %
b1000000000000000010000000 !
#640
0"
#650
1"
#655
b100000000000000110010011 %
b1000000000000000010000100 !
#660
0"
#670
1"
#675
b11111110111110001011001100011 %
b1000000000000000010001000 !
#680
0"
#690
1"
#695
b10010011 %
b1000000000000000010001100 !
#700
0"
#710
1"
#715
b1111111111100001010111100010011 %
b1000000000000000010010000 !
#720
0"
#730
1"
#735
b100000000111010010011 %
b1000000000000000010010100 !
#740
0"
#750
1"
#755
b100100000000000110010011 %
b1000000000000000010011000 !
#760
0"
#770
1"
#775
b11101110111110001110001100011 %
b1000000000000000010011100 !
#780
0"
#790
1"
#795
b10000000000000000000000010110111 %
b1000000000000000010100000 !
#800
0"
#810
1"
#815
b11111111111100001000000010010011 %
b1000000000000000010100100 !
#820
0"
#830
1"
#835
b1010111100010011 %
b1000000000000000010101000 !
#840
0"
#850
1"
#855
b111010010011 %
b1000000000000000010101100 !
#860
0"
#870
1"
#875
b101000000000000110010011 %
b1000000000000000010110000 !
#880
0"
#890
1"
#895
b11101110111110001000001100011 %
b1000000000000000010110100 !
#900
0"
#910
1"
#915
b10000000000000000000000010110111 %
b1000000000000000010111000 !
#920
0"
#930
1"
#935
b11111111111100001000000010010011 %
b1000000000000000010111100 !
#940
0"
#950
1"
#955
b1111111111100001010111100010011 %
b1000000000000000011000000 !
#960
0"
#970
1"
#975
b111010010011 %
b1000000000000000011000100 !
#980
0"
#990
1"
#995
b101100000000000110010011 %
b1000000000000000011001000 !
#1000
0"
#1010
1"
#1015
b11011110111110001010001100011 %
b1000000000000000011001100 !
#1020
0"
#1030
1"
#1035
b10000000000000000000000010110111 %
b1000000000000000011010000 !
#1040
0"
#1050
1"
#1055
b1111111111100001010111100010011 %
b1000000000000000011010100 !
#1060
0"
#1070
1"
#1075
b100000000111010010011 %
b1000000000000000011011000 !
#1080
0"
#1090
1"
#1095
b110000000000000110010011 %
b1000000000000000011011100 !
#1100
0"
#1110
1"
#1115
b11001110111110001101001100011 %
b1000000000000000011100000 !
#1120
0"
#1130
1"
#1135
b10000000000000000000000010110111 %
b1000000000000000011100100 !
#1140
0"
#1150
1"
#1155
b11111111111100001000000010010011 %
b1000000000000000011101000 !
#1160
0"
#1170
1"
#1175
b10000000000000001010111100010011 %
b1000000000000000011101100 !
#1180
0"
#1190
1"
#1195
b111010010011 %
b1000000000000000011110000 !
#1200
0"
#1210
1"
#1215
b110100000000000110010011 %
b1000000000000000011110100 !
#1220
0"
#1230
1"
#1235
b10111110111110001111001100011 %
b1000000000000000011111000 !
#1240
0"
#1250
1"
#1255
b10010011 %
b1000000000000000011111100 !
#1260
0"
#1270
1"
#1275
b11111111111100001010111100010011 %
b1000000000000000100000000 !
#1280
0"
#1290
1"
#1295
b111010010011 %
b1000000000000000100000100 !
#1300
0"
#1310
1"
#1315
b111000000000000110010011 %
b1000000000000000100001000 !
#1320
0"
#1330
1"
#1335
b10111110111110001010001100011 %
b1000000000000000100001100 !
#1340
0"
#1350
1"
#1355
b11111111111100000000000010010011 %
b1000000000000000100010000 !
#1360
0"
#1370
1"
#1375
b100001010111100010011 %
b1000000000000000100010100 !
#1380
0"
#1390
1"
#1395
b100000000111010010011 %
b1000000000000000100011000 !
#1400
0"
#1410
1"
#1415
b111100000000000110010011 %
b1000000000000000100011100 !
#1420
0"
#1430
1"
#1435
b10101110111110001101001100011 %
b1000000000000000100100000 !
#1440
0"
#1450
1"
#1455
b11111111111100000000000010010011 %
b1000000000000000100100100 !
#1460
0"
#1470
1"
#1475
b11111111111100001010111100010011 %
b1000000000000000100101000 !
#1480
0"
#1490
1"
#1495
b111010010011 %
b1000000000000000100101100 !
#1500
0"
#1510
1"
#1515
b1000000000000000110010011 %
b1000000000000000100110000 !
#1520
0"
#1530
1"
#1535
b10101110111110001000001100011 %
b1000000000000000100110100 !
#1540
0"
#1550
1"
#1555
b101100000000000010010011 %
b1000000000000000100111000 !
#1560
0"
#1570
1"
#1575
b110100001010000010010011 %
b1000000000000000100111100 !
#1580
0"
#1590
1"
#1595
b100000000111010010011 %
b1000000000000000101000000 !
#1600
0"
#1610
1"
#1615
b1000100000000000110010011 %
b1000000000000000101000100 !
#1620
0"
#1630
1"
#1635
b10011110100001001011001100011 %
b1000000000000000101001000 !
#1640
0"
#1650
1"
#1655
b1000010011 %
b1000000000000000101001100 !
#1660
0"
#1670
1"
#1675
b111100000000000010010011 %
b1000000000000000101010000 !
#1680
0"
#1690
1"
#1695
b101000001010111100010011 %
b1000000000000000101010100 !
#1700
0"
#1710
1"
#1715
b11110000001100010011 %
b1000000000000000101011000 !
#1720
0"
#1730
1"
#1735
b100100000001000010011 %
b1000000000000000101011100 !
#1740
0"
#1750
1"
#1755
b1000000000001010010011 %
b1000000000000000101100000 !
#1760
0"
#1770
1"
#1775
b11111110010100100001011011100011 %
b1000000000000000101100100 !
#1780
0"
#1790
1"
#1795
b111010010011 %
b1000000000000000101101000 !
#1800
0"
#1810
1"
#1815
b1001000000000000110010011 %
b1000000000000000101101100 !
#1820
0"
#1830
1"
#1835
b10001110100110001001001100011 %
b1000000000000000101110000 !
#1840
0"
#1850
1"
#1855
b1000010011 %
b1000000000000000101110100 !
#1860
0"
#1870
1"
#1875
b101000000000000010010011 %
b1000000000000000101111000 !
#1880
0"
#1890
1"
#1895
b1000000001010111100010011 %
b1000000000000000101111100 !
#1900
0"
#1910
1"
#1915
b10011 %
b1000000000000000110000000 !
#1920
0"
#1930
1"
#1935
b11110000001100010011 %
b1000000000000000110000100 !
#1940
0"
#1950
1"
#1955
b100100000001000010011 %
b1000000000000000110001000 !
#1960
0"
#1970
1"
#1975
b1000000000001010010011 %
b1000000000000000110001100 !
#1980
0"
#1990
1"
#1995
b11111110010100100001010011100011 %
b1000000000000000110010000 !
#2000
0"
#2010
1"
#2015
b100000000111010010011 %
b1000000000000000110010100 !
#2020
0"
#2030
1"
#2035
b1001100000000000110010011 %
b1000000000000000110011000 !
#2040
0"
#2050
1"
#2055
b1101110100110001110001100011 %
b1000000000000000110011100 !
#2060
0"
#2070
1"
#2075
b1000010011 %
b1000000000000000110100000 !
#2080
0"
#2090
1"
#2095
b1000000000000000010010011 %
b1000000000000000110100100 !
#2100
0"
#2110
1"
#2115
b100100001010111100010011 %
b1000000000000000110101000 !
#2120
0"
#2130
1"
#2135
b10011 %
b1000000000000000110101100 !
#2140
0"
#2150
1"
#2155
b1000000000000000110110000 !
#2160
0"
#2170
1"
#2175
b11110000001100010011 %
b1000000000000000110110100 !
#2180
0"
#2190
1"
#2195
b100100000001000010011 %
b1000000000000000110111000 !
#2200
0"
#2210
1"
#2215
b1000000000001010010011 %
b1000000000000000110111100 !
#2220
0"
#2230
1"
#2235
b11111110010100100001001011100011 %
b1000000000000000111000000 !
#2240
0"
#2250
1"
#2255
b111010010011 %
b1000000000000000111000100 !
#2260
0"
#2270
1"
#2275
b1010000000000000110010011 %
b1000000000000000111001000 !
#2280
0"
#2290
1"
#2295
b1011110100110001010001100011 %
b1000000000000000111001100 !
#2300
0"
#2310
1"
#2315
b1000010011 %
b1000000000000000111010000 !
#2320
0"
#2330
1"
#2335
b101100000000000010010011 %
b1000000000000000111010100 !
#2340
0"
#2350
1"
#2355
b111100001010111100010011 %
b1000000000000000111011000 !
#2360
0"
#2370
1"
#2375
b100100000001000010011 %
b1000000000000000111011100 !
#2380
0"
#2390
1"
#2395
b1000000000001010010011 %
b1000000000000000111100000 !
#2400
0"
#2410
1"
#2415
b11111110010100100001100011100011 %
b1000000000000000111100100 !
#2420
0"
#2430
1"
#2435
b100000000111010010011 %
b1000000000000000111101000 !
#2440
0"
#2450
1"
#2455
b1010100000000000110010011 %
b1000000000000000111101100 !
#2460
0"
#2470
1"
#2475
b1001110111110001001001100011 %
b1000000000000000111110000 !
#2480
0"
#2490
1"
#2495
b1000010011 %
b1000000000000000111110100 !
#2500
0"
#2510
1"
#2515
b1000100000000000010010011 %
b1000000000000000111111000 !
#2520
0"
#2530
1"
#2535
b10011 %
b1000000000000000111111100 !
#2540
0"
#2550
1"
#2555
b100000001010111100010011 %
b1000000000000001000000000 !
#2560
0"
#2570
1"
#2575
b100100000001000010011 %
b1000000000000001000000100 !
#2580
0"
#2590
1"
#2595
b1000000000001010010011 %
b1000000000000001000001000 !
#2600
0"
#2610
1"
#2615
b11111110010100100001011011100011 %
b1000000000000001000001100 !
#2620
0"
#2630
1"
#2635
b111010010011 %
b1000000000000001000010000 !
#2640
0"
#2650
1"
#2655
b1011000000000000110010011 %
b1000000000000001000010100 !
#2660
0"
#2670
1"
#2675
b101110111110001111001100011 %
b1000000000000001000011000 !
#2680
0"
#2690
1"
#2695
b1000010011 %
b1000000000000001000011100 !
#2700
0"
#2710
1"
#2715
b110000000000000010010011 %
b1000000000000001000100000 !
#2720
0"
#2730
1"
#2735
b10011 %
b1000000000000001000100100 !
#2740
0"
#2750
1"
#2755
b1000000000000001000101000 !
#2760
0"
#2770
1"
#2775
b111000001010111100010011 %
b1000000000000001000101100 !
#2780
0"
#2790
1"
#2795
b100100000001000010011 %
b1000000000000001000110000 !
#2800
0"
#2810
1"
#2815
b1000000000001010010011 %
b1000000000000001000110100 !
#2820
0"
#2830
1"
#2835
b11111110010100100001010011100011 %
b1000000000000001000111000 !
#2840
0"
#2850
1"
#2855
b100000000111010010011 %
b1000000000000001000111100 !
#2860
0"
#2870
1"
#2875
b1011100000000000110010011 %
b1000000000000001001000000 !
#2880
0"
#2890
1"
#2895
b11110111110001100001100011 %
b1000000000000001001000100 !
#2900
0"
#2910
1"
#2915
b11111111111100000010000010010011 %
b1000000000000001001001000 !
#2920
0"
#2930
1"
#2935
b111010010011 %
b1000000000000001001001100 !
#2940
0"
#2950
1"
#2955
b1100000000000000110010011 %
b1000000000000001001010000 !
#2960
0"
#2970
1"
#2975
b11110100001001000001100011 %
b1000000000000001001010100 !
#2980
0"
#2990
1"
#2995
b111111110000000010110111 %
b1000000000000001001011000 !
#3000
0"
#3010
1"
#3015
b1111111100001000000010010011 %
b1000000000000001001011100 !
#3020
0"
#3030
1"
#3035
b11111111111100001010000000010011 %
b1000000000000001001100000 !
#3040
0"
#3050
1"
#3055
b111010010011 %
b1000000000000001001100100 !
#3060
0"
#3070
1"
#3075
b1100100000000000110010011 %
b1000000000000001001101000 !
#3080
0"
#3090
1"
#3095
b1110100000001010001100011 %
b1000000000000001001101100 !
#3100
0"
#3110
1"
#3115
b1100000001110001100011 %
b1000000000000001001110000 !
#3120
0"
#3130
1"
#3135
b1111111100000000000000001111 %
b1000000000000001001110100 !
#3140
0"
#3150
1"
#3155
b11000000001100011 %
b1000000000000001001111000 !
#3160
0"
#3170
1"
#3175
b100011001000110010011 %
b1000000000000001001111100 !
#3180
0"
#3190
1"
#3195
b100011110000110010011 %
b1000000000000001010000000 !
#3200
0"
#3210
1"
#3215
b1110011 %
b1000000000000001010000100 !
#3220
0"
#3230
1"
#3235
b1111111100000000000000001111 %
b1000000000000001010001000 !
#3240
0"
#3250
1"
#3255
b100000000000110010011 %
b1000000000000001010001100 !
#3260
0"
#3270
1"
#3275
b1110011 %
b1000000000000001010010000 !
#3280
0"
#3290
1"
#3295
b11000000000000000001000001110011 %
b1000000000000001010010100 !
#3300
0"
#3310
1"
#3315
b0 %
b1000000000000001010011000 !
#3320
0"
#3330
1"
#3335
b1000000000000001010011100 !
#3340
0"
#3350
1"
#3355
b1000000000000001010100000 !
#3360
0"
#3370
1"
#3375
b1000000000000001010100100 !
#3380
0"
#3390
1"
#3395
b1000000000000001010101000 !
#3400
0"
#3410
1"
#3415
b1000000000000001010101100 !
#3420
0"
#3430
1"
#3435
b1000000000000001010110000 !
#3440
0"
#3450
1"
#3455
b1000000000000001010110100 !
#3460
0"
#3470
1"
#3475
b1000000000000001010111000 !
#3480
0"
#3490
1"
#3495
b1000000000000001010111100 !
#3500
0"
#3510
1"
#3515
b1000000000000001011000000 !
#3520
0"
#3530
1"
#3535
b1000000000000001011000100 !
#3540
0"
#3550
1"
#3555
b1000000000000001011001000 !
#3560
0"
#3570
1"
#3575
b1000000000000001011001100 !
#3580
0"
#3590
1"
#3595
b1000000000000001011010000 !
#3600
0"
#3610
1"
#3615
b1000000000000001011010100 !
#3620
0"
#3630
1"
#3635
b1000000000000001011011000 !
#3640
0"
#3650
1"
#3655
b1000000000000001011011100 !
#3660
0"
#3670
1"
#3675
b1000000000000001011100000 !
#3680
0"
#3690
1"
#3695
b1000000000000001011100100 !
#3700
0"
#3710
1"
#3715
b1000000000000001011101000 !
#3720
0"
#3730
1"
#3735
b1000000000000001011101100 !
#3740
0"
#3750
1"
#3755
b1000000000000001011110000 !
#3760
0"
#3770
1"
#3775
b1000000000000001011110100 !
#3780
0"
#3790
1"
#3795
b1000000000000001011111000 !
#3800
0"
#3810
1"
#3815
b1000000000000001011111100 !
#3820
0"
#3830
1"
#3835
b1000000000000001100000000 !
#3840
0"
#3850
1"
#3855
b1000000000000001100000100 !
#3860
0"
#3870
1"
#3875
b1000000000000001100001000 !
#3880
0"
#3890
1"
#3895
b1000000000000001100001100 !
#3900
0"
#3910
1"
#3915
b1000000000000001100010000 !
#3920
0"
#3930
1"
#3935
b1000000000000001100010100 !
#3940
0"
#3950
1"
#3955
b1000000000000001100011000 !
#3960
0"
#3970
1"
#3975
b1000000000000001100011100 !
#3980
0"
#3990
1"
#3995
b1000000000000001100100000 !
#4000
0"
#4010
1"
#4015
b1000000000000001100100100 !
#4020
0"
#4030
1"
#4035
b1000000000000001100101000 !
#4040
0"
#4050
1"
#4055
b1000000000000001100101100 !
#4060
0"
#4070
1"
#4075
b1000000000000001100110000 !
#4080
0"
#4090
1"
#4095
b1000000000000001100110100 !
#4100
0"
#4110
1"
#4115
b1000000000000001100111000 !
#4120
0"
#4130
1"
#4135
b1000000000000001100111100 !
#4140
0"
#4150
1"
#4155
b1000000000000001101000000 !
#4160
0"
#4170
1"
#4175
b1000000000000001101000100 !
#4180
0"
#4190
1"
#4195
b1000000000000001101001000 !
#4200
0"
#4210
1"
#4215
b1000000000000001101001100 !
#4220
0"
#4230
1"
#4235
b1000000000000001101010000 !
#4240
0"
#4250
1"
#4255
bx %
b1000000000000001101010100 !
#4260
0"
#4270
1"
#4275
b1000000000000001101011000 !
#4280
0"
#4290
1"
#4295
b1000000000000001101011100 !
#4300
0"
#4310
1"
#4315
b1000000000000001101100000 !
#4320
0"
#4330
1"
#4335
b1000000000000001101100100 !
#4340
0"
#4350
1"
#4355
b1000000000000001101101000 !
#4360
0"
#4370
1"
#4375
b1000000000000001101101100 !
#4380
0"
#4390
1"
#4395
b1000000000000001101110000 !
#4400
0"
#4410
1"
#4415
b1000000000000001101110100 !
#4420
0"
#4430
1"
#4435
b1000000000000001101111000 !
#4440
0"
#4450
1"
#4455
b1000000000000001101111100 !
#4460
0"
#4470
1"
#4475
b1000000000000001110000000 !
#4480
0"
#4490
1"
#4495
b1000000000000001110000100 !
#4500
0"
#4510
1"
#4515
b1000000000000001110001000 !
#4520
0"
#4530
1"
#4535
b1000000000000001110001100 !
#4540
0"
#4550
1"
#4555
b1000000000000001110010000 !
#4560
0"
#4570
1"
#4575
b1000000000000001110010100 !
#4580
0"
#4590
1"
#4595
b1000000000000001110011000 !
#4600
0"
#4610
1"
#4615
b1000000000000001110011100 !
#4620
0"
#4630
1"
#4635
b1000000000000001110100000 !
#4640
0"
#4650
1"
#4655
b1000000000000001110100100 !
#4660
0"
#4670
1"
#4675
b1000000000000001110101000 !
#4680
0"
#4690
1"
#4695
b1000000000000001110101100 !
#4700
0"
#4710
1"
#4715
b1000000000000001110110000 !
#4720
0"
#4730
1"
#4735
b1000000000000001110110100 !
#4740
0"
#4750
1"
#4755
b1000000000000001110111000 !
#4760
0"
#4770
1"
#4775
b1000000000000001110111100 !
#4780
0"
#4790
1"
#4795
b1000000000000001111000000 !
#4800
0"
#4810
1"
#4815
b1000000000000001111000100 !
#4820
0"
#4830
1"
#4835
b1000000000000001111001000 !
#4840
0"
#4850
1"
#4855
b1000000000000001111001100 !
#4860
0"
#4870
1"
#4875
b1000000000000001111010000 !
#4880
0"
#4890
1"
#4895
b1000000000000001111010100 !
#4900
0"
#4910
1"
#4915
b1000000000000001111011000 !
#4920
0"
#4930
1"
#4935
b1000000000000001111011100 !
#4940
0"
#4950
1"
#4955
b1000000000000001111100000 !
#4960
0"
#4970
1"
#4975
b1000000000000001111100100 !
#4980
0"
#4990
1"
#4995
b1000000000000001111101000 !
#5000
0"
#5010
1"
#5015
b1000000000000001111101100 !
#5020
0"
#5030
1"
#5035
b1000000000000001111110000 !
#5040
0"
#5050
1"
#5055
b1000000000000001111110100 !
#5060
0"
#5070
1"
#5075
b1000000000000001111111000 !
#5080
0"
#5090
1"
#5095
b1000000000000001111111100 !
#5100
0"
#5110
1"
#5115
b1000000000000010000000000 !
#5120
0"
#5130
1"
#5135
b1000000000000010000000100 !
#5140
0"
#5150
1"
#5155
b1000000000000010000001000 !
#5160
0"
#5170
1"
#5175
b1000000000000010000001100 !
#5180
0"
#5190
1"
#5195
b1000000000000010000010000 !
#5200
0"
#5210
1"
#5215
b1000000000000010000010100 !
#5220
0"
#5230
1"
#5235
b1000000000000010000011000 !
#5240
0"
#5250
1"
#5255
b1000000000000010000011100 !
#5260
0"
#5270
1"
#5275
b1000000000000010000100000 !
#5280
0"
#5290
1"
#5295
b1000000000000010000100100 !
#5300
0"
#5310
1"
#5315
b1000000000000010000101000 !
#5320
0"
#5330
1"
#5335
b1000000000000010000101100 !
#5340
0"
#5350
1"
#5355
b1000000000000010000110000 !
#5360
0"
#5370
1"
#5375
b1000000000000010000110100 !
#5380
0"
#5390
1"
#5395
b1000000000000010000111000 !
#5400
0"
#5410
1"
#5415
b1000000000000010000111100 !
#5420
0"
#5430
1"
#5435
b1000000000000010001000000 !
#5440
0"
#5450
1"
#5455
b1000000000000010001000100 !
#5460
0"
#5470
1"
#5475
b1000000000000010001001000 !
#5480
0"
#5490
1"
#5495
b1000000000000010001001100 !
#5500
0"
#5510
1"
#5515
b1000000000000010001010000 !
#5520
0"
#5530
1"
#5535
b1000000000000010001010100 !
#5540
0"
#5550
1"
#5555
b1000000000000010001011000 !
#5560
0"
#5570
1"
#5575
b1000000000000010001011100 !
#5580
0"
#5590
1"
#5595
b1000000000000010001100000 !
#5600
0"
#5610
1"
#5615
b1000000000000010001100100 !
#5620
0"
#5630
1"
#5635
b1000000000000010001101000 !
#5640
0"
#5650
1"
#5655
b1000000000000010001101100 !
#5660
0"
#5670
1"
#5675
b1000000000000010001110000 !
#5680
0"
#5690
1"
#5695
b1000000000000010001110100 !
#5700
0"
#5710
1"
#5715
b1000000000000010001111000 !
#5720
0"
#5730
1"
#5735
b1000000000000010001111100 !
#5740
0"
#5750
1"
#5755
b1000000000000010010000000 !
#5760
0"
#5770
1"
#5775
b1000000000000010010000100 !
#5780
0"
#5790
1"
#5795
b1000000000000010010001000 !
#5800
0"
#5810
1"
#5815
b1000000000000010010001100 !
#5820
0"
#5830
1"
#5835
b1000000000000010010010000 !
#5840
0"
#5850
1"
#5855
b1000000000000010010010100 !
#5860
0"
#5870
1"
#5875
b1000000000000010010011000 !
#5880
0"
#5890
1"
#5895
b1000000000000010010011100 !
#5900
0"
#5910
1"
#5915
b1000000000000010010100000 !
#5920
0"
#5930
1"
#5935
b1000000000000010010100100 !
#5940
0"
#5950
1"
#5955
b1000000000000010010101000 !
#5960
0"
#5970
1"
#5975
b1000000000000010010101100 !
#5980
0"
#5990
1"
#5995
b1000000000000010010110000 !
#6000
0"
#6010
1"
#6015
b1000000000000010010110100 !
#6020
0"
#6030
1"
#6035
b1000000000000010010111000 !
#6040
0"
#6050
1"
#6055
b1000000000000010010111100 !
#6060
0"
#6070
1"
#6075
b1000000000000010011000000 !
#6080
0"
#6090
1"
#6095
b1000000000000010011000100 !
#6100
0"
#6110
1"
#6115
b1000000000000010011001000 !
#6120
0"
#6130
1"
#6135
b1000000000000010011001100 !
#6140
0"
#6150
1"
#6155
b1000000000000010011010000 !
#6160
0"
#6170
1"
#6175
b1000000000000010011010100 !
#6180
0"
#6190
1"
#6195
b1000000000000010011011000 !
#6200
0"
#6210
1"
#6215
b1000000000000010011011100 !
#6220
0"
#6230
1"
#6235
b1000000000000010011100000 !
#6240
0"
#6250
1"
#6255
b1000000000000010011100100 !
#6260
0"
#6270
1"
#6275
b1000000000000010011101000 !
#6280
0"
#6290
1"
#6295
b1000000000000010011101100 !
#6300
0"
#6310
1"
#6315
b1000000000000010011110000 !
#6320
0"
#6330
1"
#6335
b1000000000000010011110100 !
#6340
0"
#6350
1"
#6355
b1000000000000010011111000 !
#6360
0"
#6370
1"
#6375
b1000000000000010011111100 !
#6380
0"
#6390
1"
#6395
b1000000000000010100000000 !
#6400
0"
#6410
1"
#6415
b1000000000000010100000100 !
#6420
0"
#6430
1"
#6435
b1000000000000010100001000 !
#6440
0"
#6450
1"
#6455
b1000000000000010100001100 !
#6460
0"
#6470
1"
#6475
b1000000000000010100010000 !
#6480
0"
#6490
1"
#6495
b1000000000000010100010100 !
#6500
0"
#6510
1"
#6515
b1000000000000010100011000 !
#6520
0"
#6530
1"
#6535
b1000000000000010100011100 !
#6540
0"
#6550
1"
#6555
b1000000000000010100100000 !
#6560
0"
#6570
1"
#6575
b1000000000000010100100100 !
#6580
0"
#6590
1"
#6595
b1000000000000010100101000 !
#6600
0"
#6610
1"
#6615
b1000000000000010100101100 !
#6620
0"
#6630
1"
#6635
b1000000000000010100110000 !
#6640
0"
#6650
1"
#6655
b1000000000000010100110100 !
#6660
0"
#6670
1"
#6675
b1000000000000010100111000 !
#6680
0"
#6690
1"
#6695
b1000000000000010100111100 !
#6700
0"
#6710
1"
#6715
b1000000000000010101000000 !
#6720
0"
#6730
1"
#6735
b1000000000000010101000100 !
#6740
0"
#6750
1"
#6755
b1000000000000010101001000 !
#6760
0"
#6770
1"
#6775
b1000000000000010101001100 !
#6780
0"
#6790
1"
#6795
b1000000000000010101010000 !
#6800
0"
#6810
1"
#6815
b1000000000000010101010100 !
#6820
0"
#6830
1"
#6835
b1000000000000010101011000 !
#6840
0"
#6850
1"
#6855
b1000000000000010101011100 !
#6860
0"
#6870
1"
#6875
b1000000000000010101100000 !
#6880
0"
#6890
1"
#6895
b1000000000000010101100100 !
#6900
0"
#6910
1"
#6915
b1000000000000010101101000 !
#6920
0"
#6930
1"
#6935
b1000000000000010101101100 !
#6940
0"
#6950
1"
#6955
b1000000000000010101110000 !
#6960
0"
#6970
1"
#6975
b1000000000000010101110100 !
#6980
0"
#6990
1"
#6995
b1000000000000010101111000 !
#7000
0"
#7010
1"
#7015
b1000000000000010101111100 !
#7020
0"
#7030
1"
#7035
b1000000000000010110000000 !
#7040
0"
#7050
1"
#7055
b1000000000000010110000100 !
#7060
0"
#7070
1"
#7075
b1000000000000010110001000 !
#7080
0"
#7090
1"
#7095
b1000000000000010110001100 !
#7100
0"
#7110
1"
#7115
b1000000000000010110010000 !
#7120
0"
#7130
1"
#7135
b1000000000000010110010100 !
#7140
0"
#7150
1"
#7155
b1000000000000010110011000 !
#7160
0"
#7170
1"
#7175
b1000000000000010110011100 !
#7180
0"
#7190
1"
#7195
b1000000000000010110100000 !
#7200
0"
#7210
1"
#7215
b1000000000000010110100100 !
#7220
0"
#7230
1"
#7235
b1000000000000010110101000 !
#7240
0"
#7250
1"
#7255
b1000000000000010110101100 !
#7260
0"
#7270
1"
#7275
b1000000000000010110110000 !
#7280
0"
#7290
1"
#7295
b1000000000000010110110100 !
#7300
0"
#7310
1"
#7315
b1000000000000010110111000 !
#7320
0"
#7330
1"
#7335
b1000000000000010110111100 !
#7340
0"
#7350
1"
#7355
b1000000000000010111000000 !
#7360
0"
#7370
1"
#7375
b1000000000000010111000100 !
#7380
0"
#7390
1"
#7395
b1000000000000010111001000 !
#7400
0"
#7410
1"
#7415
b1000000000000010111001100 !
#7420
0"
#7430
1"
#7435
b1000000000000010111010000 !
#7440
0"
#7450
1"
#7455
b1000000000000010111010100 !
#7460
0"
#7470
1"
#7475
b1000000000000010111011000 !
#7480
0"
#7490
1"
