PROJ/PD2/fetch-and-decode/fetch-decode.v
`define FILE_PATH "../../rv32-benchmarks-master/simple-programs/SumArray.x"
`define FILE_LINES 39
`define VCD "fetch-decode-SumArray.vcd"

`define MEM_DEPTH_BYTES 'h0100000
`define STARTING_ADDR 'h01000000

`define READ 0
`define WRITE 1

`define HALF_CYCLE 10

/*========================================================================================*/

// main memory component
module mainmem (
	input clock,
	input [31:0] address,
	input [31:0] data_in,
	output [31:0] data_out,
	input read_write); 

	wire read_write;
	wire [31:0] address;
	wire [31:0] data_in;
	reg [31:0] data_out;

	reg [7:0] mem[0:`MEM_DEPTH_BYTES - 1];

    // read mode
	always @(clock or address or read_write) begin
		if (read_write == `READ)
			data_out <= {
				mem[address - `STARTING_ADDR + 3],
				mem[address - `STARTING_ADDR + 2],
				mem[address - `STARTING_ADDR + 1],
				mem[address - `STARTING_ADDR]
			};
		else
			data_out <= 32'hXXXXXXXX;
	end

	// write mode
    always @(posedge clock) begin
        if (read_write == `WRITE) begin
            mem[address - `STARTING_ADDR + 3] <= data_in[31:24];
            mem[address - `STARTING_ADDR + 2] <= data_in[23:16];
            mem[address - `STARTING_ADDR + 1] <= data_in[15:8];
            mem[address - `STARTING_ADDR] <= data_in[7:0];
        end
	end

	// testbench
	reg [31:0] tmp_mem[0:(`MEM_DEPTH_BYTES / 4) - 1];
	integer i;
    
    initial begin
        $readmemh(`FILE_PATH, tmp_mem);

		// copy to mem
		i = 0;
		while (tmp_mem[i] !== 32'hX) begin
			mem[(4 * i) + 3] <= tmp_mem[i][31:24];
            mem[(4 * i) + 2] <= tmp_mem[i][23:16];
            mem[(4 * i) + 1] <= tmp_mem[i][15:8];
            mem[(4 * i)] <= tmp_mem[i][7:0];
			i += 1;
		end
    end
endmodule // mainmem

/*========================================================================================*/

// fetch component
module fetch (
	input clock,
	input fetch_en,
	input [31:0] pc_in,
	output [31:0] pc_out,
	output [31:0] fetch_out);

	wire [31:0] pc_out;

	initial begin
		$dumpfile(`VCD);
        $dumpvars(0, mem);
    end

	assign pc_out = pc_in + ({32{fetch_en}} & 4);

	mainmem mem(
		.clock(clock),
		.address(pc_in),
		.data_in(32'hXXXXXXXX),
		.data_out(fetch_out),
		.read_write(~fetch_en));

endmodule // fetch

/*========================================================================================*/

// decode component
module decode (
	input clock,
	input [31:0] pc,
	input [31:0] decode_in);

	wire [31:0] pc;

	wire [6:0] opcode;
	wire [2:0] funct3;
	wire [6:0] funct7;

	wire [4:0] rd;
	wire [4:0] rs1;
	wire [4:0] rs2;

	// wire signed [11:0] imm_i;
	// wire signed [11:0] imm_s;
	// wire signed [4:0] imm_u;
	wire signed [31:0] imm_i;
	wire signed [31:0] imm_s;
	wire signed [31:0] imm_u;

	wire 		[4:0] shamt;
	// wire signed [12:0] addr_b;
	// wire signed [31:0] addr_j;
	wire signed [31:0] addr_b;
	wire signed [31:0] addr_j;

	assign opcode = decode_in[6:0];
	assign funct3 = decode_in[14:12];
	assign funct7 = decode_in[31:25];

	assign rd = decode_in[11:7];
	assign rs1 = decode_in[19:15];
	assign rs2 = decode_in[24:20];

	assign imm_i = { {20{decode_in[31]}}, decode_in[31:20] };
	assign imm_s = { {20{decode_in[31]}}, decode_in[31:25], decode_in[11:7] };
	assign imm_u = { {12{decode_in[31]}}, decode_in[31:12] };

	assign shamt = rs2;
	assign addr_b = pc + { {19{decode_in[31]}}, decode_in[31], decode_in[7], decode_in[30:25], decode_in[11:8], 1'b0 };
								//   1             1                 6                4     1
	assign addr_j = pc + { {11{decode_in[31]}}, decode_in[31], decode_in[19:12], decode_in[20], decode_in[30:21], 1'b0 };

	always @(decode_in) begin
		#1
		if (opcode == 7'b0110111)
			#1 $display("pc: 0x%8h\tinstr: 0x%8h\tlui\tx%0d, 0x%0h",
							pc, decode_in, rd, imm_u); // LUI

		else if (opcode == 7'b0010111)
			#1 $display("pc: 0x%8h\tinstr: 0x%8h\tauipc\tx%0d, 0x%0h",
							pc, decode_in, rd, imm_u); // AUIPC

		else if (opcode == 7'b1101111) begin
			#1 $display("pc: 0x%8h\tinstr: 0x%8h\tjal\tx%0d, 0x%8h",
							pc, decode_in, rd, addr_j); // JAL
		end

		else if (opcode == 7'b1100111)
			#1 $display("pc: 0x%8h\tinstr: 0x%8h\tjalr\tx%0d, %0d(x%0d)",
							pc, decode_in, rd, imm_i, rs1); // JALR

		else if (opcode == 7'b1100011) begin
			if (funct3 == 3'b000)
				#1 $display("pc: 0x%8h\tinstr: 0x%8h\tbeq\tx%0d, x%0d, 0x%8h",
								pc, decode_in, rs1, rs2, addr_b); // BEQ
			else if (funct3 == 3'b001)
				#1 $display("pc: 0x%8h\tinstr: 0x%8h\tbne\tx%0d, x%0d, 0x%8h",
								pc, decode_in, rs1, rs2, addr_b); // BNE
			else if (funct3 == 3'b100)
				#1 $display("pc: 0x%8h\tinstr: 0x%8h\tblt\tx%0d, x%0d, 0x%8h",
								pc, decode_in, rs1, rs2, addr_b); // BLT
			else if (funct3 == 3'b101)
				#1 $display("pc: 0x%8h\tinstr: 0x%8h\tbge\tx%0d, x%0d, 0x%8h",
								pc, decode_in, rs1, rs2, addr_b); // BGE
			else if (funct3 == 3'b110)
				#1 $display("pc: 0x%8h\tinstr: 0x%8h\tbltu\tx%0d, x%0d, 0x%8h",
								pc, decode_in, rs1, rs2, addr_b); // BLTU
			else if (funct3 == 3'b111)
				#1 $display("pc: 0x%8h\tinstr: 0x%8h\tbgeu\tx%0d, x%0d, 0x%8h",
								pc, decode_in, rs1, rs2, addr_b); // BGEU
			else begin
				#1 $display("pc: 0x%8h\tinstr: 0x%8h\tnot instr",
								pc, decode_in); // NOT INSTRUCTION
			end
		end

		else if (opcode == 7'b0000011) begin
			if (funct3 == 3'b000)
				#1 $display("pc: 0x%8h\tinstr: 0x%8h\tlb\tx%0d, %0d(x%0d)",
								pc, decode_in, rd, imm_i, rs1); // LB
			else if (funct3 == 3'b001)
				#1 $display("pc: 0x%8h\tinstr: 0x%8h\tlh\tx%0d, %0d(x%0d)",
								pc, decode_in, rd, imm_i, rs1); // LH
			else if (funct3 == 3'b010)
				#1 $display("pc: 0x%8h\tinstr: 0x%8h\tlw\tx%0d, %0d(x%0d)",
								pc, decode_in, rd, imm_i, rs1); // LW
			else if (funct3 == 3'b100)
				#1 $display("pc: 0x%8h\tinstr: 0x%8h\tlbu\tx%0d, %0d(x%0d)",
								pc, decode_in, rd, imm_i, rs1); // LBU
			else if (funct3 == 3'b101)
				#1 $display("pc: 0x%8h\tinstr: 0x%8h\tlhu\tx%0d, %0d(x%0d)",
								pc, decode_in, rd, imm_i, rs1); // LHU
			else begin
				#1 $display("pc: 0x%8h\tinstr: 0x%8h\tnot instr",
								pc, decode_in); // NOT INSTRUCTION
			end
		end

		else if (opcode == 7'b0100011) begin
			if (funct3 == 3'b000)
				#1 $display("pc: 0x%8h\tinstr: 0x%8h\tsb\tx%0d, %0d(x%0d)",
								pc, decode_in, rs2, imm_s, rs1); // SB
			else if (funct3 == 3'b001)
				#1 $display("pc: 0x%8h\tinstr: 0x%8h\tsh\tx%0d, %0d(x%0d)",
								pc, decode_in, rs2, imm_s, rs1); // SH
			else if (funct3 == 3'b010)
				#1 $display("pc: 0x%8h\tinstr: 0x%8h\tsw\tx%0d, %0d(x%0d)",
								pc, decode_in, rs2, imm_s, rs1); // SW
			else begin
				#1 $display("pc: 0x%8h\tinstr: 0x%8h\tnot instr",
								pc, decode_in); // NOT INSTRUCTION
			end
		end

		else if (opcode == 7'b0010011) begin
			if (funct3 == 3'b000)
				#1 $display("pc: 0x%8h\tinstr: 0x%8h\taddi\tx%0d, x%0d, %0d",
								pc, decode_in, rd, rs1, imm_i); // ADDI
			else if (funct3 == 3'b010)
				#1 $display("pc: 0x%8h\tinstr: 0x%8h\tslti\tx%0d, x%0d, %0d",
								pc, decode_in, rd, rs1, imm_i); // SLTI
			else if (funct3 == 3'b011)
				#1 $display("pc: 0x%8h\tinstr: 0x%8h\tsltiu\tx%0d, x%0d, %0d",
								pc, decode_in, rd, rs1, imm_i); // SLTIU
			else if (funct3 == 3'b100)
				#1 $display("pc: 0x%8h\tinstr: 0x%8h\txori\tx%0d, x%0d, %0d",
								pc, decode_in, rd, rs1, imm_i); // XORI
			else if (funct3 == 3'b110)
				#1 $display("pc: 0x%8h\tinstr: 0x%8h\tori\tx%0d, x%0d, %0d",
								pc, decode_in, rd, rs1, imm_i); // ORI
			else if (funct3 == 3'b111)
				#1 $display("pc: 0x%8h\tinstr: 0x%8h\tandi\tx%0d, x%0d, %0d",
								pc, decode_in, rd, rs1, imm_i); // ANDI
			else if (funct3 == 3'b001 && funct7 == 7'b0000000)
				#1 $display("pc: 0x%8h\tinstr: 0x%8h\tslli\tx%0d, x%0d, 0x%0h",
								pc, decode_in, rd, rs1, shamt); // SLLI
			else if (funct3 == 3'b101 && funct7 == 7'b0000000)
				#1 $display("pc: 0x%8h\tinstr: 0x%8h\tsrli\tx%0d, x%0d, 0x%0h",
								pc, decode_in, rd, rs1, shamt); // SRLI
			else if (funct3 == 3'b101 && funct7 == 7'b0100000)
				#1 $display("pc: 0x%8h\tinstr: 0x%8h\tsrai\tx%0d, x%0d, 0x%0h",
								pc, decode_in, rd, rs1, shamt); // SRAI
			else begin
				#1 $display("pc: 0x%8h\tinstr: 0x%8h\tnot instr",
								pc, decode_in); // NOT INSTRUCTION
			end
		end
		
		else if (opcode == 7'b0110011) begin
			if (funct3 == 3'b000 && funct7 == 7'b0000000)
				#1 $display("pc: 0x%8h\tinstr: 0x%8h\tadd\tx%0d, x%0d, x%0d",
								pc, decode_in, rd, rs1, rs2); // ADD
			else if (funct3 == 3'b000 && funct7 == 7'b0100000)
				#1 $display("pc: 0x%8h\tinstr: 0x%8h\tsub\tx%0d, x%0d, x%0d",
								pc, decode_in, rd, rs1, rs2); // SUB
			else if (funct3 == 3'b001 && funct7 == 7'b0000000)
				#1 $display("pc: 0x%8h\tinstr: 0x%8h\tsll\tx%0d, x%0d, x%0d",
								pc, decode_in, rd, rs1, rs2); // SLL
			else if (funct3 == 3'b010 && funct7 == 7'b0000000)
				#1 $display("pc: 0x%8h\tinstr: 0x%8h\tslt\tx%0d, x%0d, x%0d",
								pc, decode_in, rd, rs1, rs2); // SLT
			else if (funct3 == 3'b011 && funct7 == 7'b0000000)
				#1 $display("pc: 0x%8h\tinstr: 0x%8h\tsltu\tx%0d, x%0d, x%0d",
								pc, decode_in, rd, rs1, rs2); // SLTU
			else if (funct3 == 3'b100 && funct7 == 7'b0000000)
				#1 $display("pc: 0x%8h\tinstr: 0x%8h\txor\tx%0d, x%0d, x%0d",
								pc, decode_in, rd, rs1, rs2); // XOR
			else if (funct3 == 3'b101 && funct7 == 7'b0000000)
				#1 $display("pc: 0x%8h\tinstr: 0x%8h\tsrl\tx%0d, x%0d, x%0d",
								pc, decode_in, rd, rs1, rs2); // SRL
			else if (funct3 == 3'b101 && funct7 == 7'b0100000)
				#1 $display("pc: 0x%8h\tinstr: 0x%8h\tsra\tx%0d, x%0d, x%0d",
								pc, decode_in, rd, rs1, rs2); // SRA
			else if (funct3 == 3'b110 && funct7 == 7'b0000000)
				#1 $display("pc: 0x%8h\tinstr: 0x%8h\tor\tx%0d, x%0d, x%0d",
								pc, decode_in, rd, rs1, rs2); // OR
			else if (funct3 == 3'b111 && funct7 == 7'b0000000)
				#1 $display("pc: 0x%8h\tinstr: 0x%8h\tand\tx%0d, x%0d, x%0d",
								pc, decode_in, rd, rs1, rs2); // AND
			else begin
				#1 $display("pc: 0x%8h\tinstr: 0x%8h\tnot instr",
								pc, decode_in); // NOT INSTRUCTION
			end
		end

		else if (decode_in == 32'b000000000000_00000_000_00000_1110011) begin
			#1 $display("pc: 0x%8h\tinstr: 0x%8h\tecall",
							pc, decode_in,); // ECALL
		end

		else begin
			// not instruction
			#1 $display("pc: 0x%8h\tinstr: 0x%8h\tnot instr",
							pc, decode_in); // NOT INSTRUCTION
		end
	end
endmodule // decode

/*========================================================================================*/

// testbench
module dut;
	reg clock = 0;
	reg [31:0] pc;
	wire [31:0] pc_next;
	wire [31:0] fet_out_dec_in;

    initial begin
        $dumpvars(0, fet);
        $dumpvars(0, dec);

		#(`HALF_CYCLE / 2) 
		pc = `STARTING_ADDR;

		#(`FILE_LINES * 4 * `HALF_CYCLE) $finish;
    end
	
	fetch fet (
		.clock(clock),
		.fetch_en(1'h1),
		.pc_in(pc),
		.pc_out(pc_next),
		.fetch_out(fet_out_dec_in));
	
	decode dec (
		.clock(clock),
		.pc(pc),
		.decode_in(fet_out_dec_in));

	always @(posedge clock) begin
		pc = pc_next;
	end
	
	always begin                 
		#`HALF_CYCLE clock = ~clock;
	end
endmodule

PROJ/PD2/fetch-and-decode/fetch-decode-SumArray.vcd
$date
	Sun May 31 17:21:14 2020
$end
$version
	Icarus Verilog
$end
$timescale
	1s
$end
$scope module dut $end
$scope module fet $end
$scope module mem $end
$var wire 32 ! address [31:0] $end
$var wire 1 " clock $end
$var wire 32 # data_in [31:0] $end
$var wire 1 $ read_write $end
$var reg 32 % data_out [31:0] $end
$var integer 32 & i [31:0] $end
$upscope $end
$upscope $end
$upscope $end
$scope module dut $end
$scope module fet $end
$var wire 1 " clock $end
$var wire 1 ' fetch_en $end
$var wire 32 ( pc_in [31:0] $end
$var wire 32 ) pc_out [31:0] $end
$var wire 32 * fetch_out [31:0] $end
$scope module mem $end
$upscope $end
$upscope $end
$upscope $end
$scope module dut $end
$scope module dec $end
$var wire 1 " clock $end
$var wire 32 + pc [31:0] $end
$var wire 5 , shamt [4:0] $end
$var wire 5 - rs2 [4:0] $end
$var wire 5 . rs1 [4:0] $end
$var wire 5 / rd [4:0] $end
$var wire 7 0 opcode [6:0] $end
$var wire 32 1 imm_u [31:0] $end
$var wire 32 2 imm_s [31:0] $end
$var wire 32 3 imm_i [31:0] $end
$var wire 7 4 funct7 [6:0] $end
$var wire 3 5 funct3 [2:0] $end
$var wire 32 6 decode_in [31:0] $end
$var wire 32 7 addr_j [31:0] $end
$var wire 32 8 addr_b [31:0] $end
$upscope $end
$upscope $end
$enddefinitions $end
#0
$dumpvars
bx 8
bx 7
bx 6
bx 5
bx 4
bx 3
bx 2
bx 1
bx 0
bx /
bx .
bx -
bx ,
bx +
bx *
bx )
bx (
1'
b111110 &
bx %
0$
bx #
0"
bx !
$end
#5
b111100010000011111000000 7
b111111111111011111000010 8
b11111111111111111100000000010000 1
b11111111111111111111111111000010 2
b11111111111111111111111111000000 3
b0 ,
b0 -
b10 .
b10 /
b1111110 4
b0 5
b10011 0
b11111100000000010000000100010011 %
b11111100000000010000000100010011 *
b11111100000000010000000100010011 6
b1000000000000000000000100 )
b1000000000000000000000000 !
b1000000000000000000000000 (
b1000000000000000000000000 +
#10
b10000100010010 1
b111100 2
b100001 3
b1 ,
b1 -
b11100 /
b1 4
b10 5
b100011 0
b10000100010010111000100011 %
b10000100010010111000100011 *
b10000100010010111000100011 6
b1000000000000000001000000 8
b1000000010010100000100100 7
b1000000000000000000001000 )
b1000000000000000000000100 !
b1000000000000000000000100 (
b1000000000000000000000100 +
1"
#20
0"
#30
b10000000010010 1
b101100 2
b100000 3
b0 ,
b0 -
b1100 /
b10000000010010011000100011 %
b10000000010010011000100011 *
b10000000010010011000100011 6
b1000000000000000000110100 8
b1000000010010000000101000 7
b1000000000000000000001100 )
b1000000000000000000001000 !
b1000000000000000000001000 (
b1000000000000000000001000 +
1"
#40
0"
#50
b101000 2
b1000 /
b10000000010010010000100011 %
b10000000010010010000100011 *
b10000000010010010000100011 6
b1000000000000000000110100 8
b1000000010010000000101100 7
b1000000000000000000010000 )
b1000000000000000000001100 !
b1000000000000000000001100 (
b1000000000000000000001100 +
1"
#60
0"
#70
b101100 2
b1100 /
b10000000010010011000100011 %
b10000000010010011000100011 *
b10000000010010011000100011 6
b1000000000000000000111100 8
b1000000010010000000110000 7
b1000000000000000000010100 )
b1000000000000000000010000 !
b1000000000000000000010000 (
b1000000000000000000010000 +
1"
#80
0"
#90
b10100000000000 1
b100000 2
b101000 3
b1000 ,
b1000 -
b0 .
b0 /
b0 5
b1101111 0
b10100000000000000001101111 %
b10100000000000000001101111 *
b10100000000000000001101111 6
b1000000000000000000110100 8
b1000000000000000000111100 7
b1000000000000000000011000 )
b1000000000000000000010100 !
b1000000000000000000010100 (
b1000000000000000000010100 +
1"
#100
0"
#110
b10110000010010 1
b101111 2
b101100 3
b1100 ,
b1100 -
b10 .
b1111 /
b10 5
b11 0
b10110000010010011110000011 %
b10110000010010011110000011 *
b10110000010010011110000011 6
b1000000000000100001000110 8
b1000000010010000001000100 7
b1000000000000000000011100 )
b1000000000000000000011000 !
b1000000000000000000011000 (
b1000000000000000000011000 +
1"
#120
0"
#130
b1001111001 1
b1111 2
b10 3
b10 ,
b10 -
b1111 .
b0 4
b1 5
b10011 0
b1001111001011110010011 %
b1001111001011110010011 *
b1001111001011110010011 6
b1000000000000100000101010 8
b1000001111001000000011110 7
b1000000000000000000100000 )
b1000000000000000000011100 !
b1000000000000000000011100 (
b1000000000000000000011100 +
1"
#140
0"
#150
b11000000010000 1
b101110 2
b110000 3
b10000 ,
b10000 -
b10 .
b1110 /
b1 4
b0 5
b11000000010000011100010011 %
b11000000010000011100010011 *
b11000000010000011100010011 6
b1000000000000000001001110 8
b1000000010000000001010000 7
b1000000000000000000100100 )
b1000000000000000000100000 !
b1000000000000000000100000 (
b1000000000000000000100000 +
1"
#160
0"
#170
b111101110000 1
b1111 2
b1111 3
b1111 ,
b1111 -
b1110 .
b1111 /
b0 4
b110011 0
b111101110000011110110011 %
b111101110000011110110011 *
b111101110000011110110011 6
b1000000000000100000110010 8
b1000001110000100000110010 7
b1000000000000000000101000 )
b1000000000000000000100100 !
b1000000000000000000100100 (
b1000000000000000000100100 +
1"
#180
0"
#190
b10110000010010 1
b101110 2
b101100 3
b1100 ,
b1100 -
b10 .
b1110 /
b1 4
b10 5
b11 0
b10110000010010011100000011 %
b10110000010010011100000011 *
b10110000010010011100000011 6
b1000000000000000001010110 8
b1000000010010000001010100 7
b1000000000000000000101100 )
b1000000000000000000101000 !
b1000000000000000000101000 (
b1000000000000000000101000 +
1"
#200
0"
#210
b11111111111111111100111001111010 1
b11111111111111111111111111010000 2
b11111111111111111111111111001110 3
b1110 ,
b1110 -
b1111 .
b10000 /
b1111110 4
b100011 0
b11111100111001111010100000100011 %
b11111100111001111010100000100011 *
b11111100111001111010100000100011 6
b111111111111011111111100 8
b111101111010011111111010 7
b1000000000000000000110000 )
b1000000000000000000101100 !
b1000000000000000000101100 (
b1000000000000000000101100 +
1"
#220
0"
#230
b10110000010010 1
b101111 2
b101100 3
b1100 ,
b1100 -
b10 .
b1111 /
b1 4
b11 0
b10110000010010011110000011 %
b10110000010010011110000011 *
b10110000010010011110000011 6
b1000000000000100001011110 8
b1000000010010000001011100 7
b1000000000000000000110100 )
b1000000000000000000110000 !
b1000000000000000000110000 (
b1000000000000000000110000 +
1"
#240
0"
#250
b101111000 1
b1111 2
b1 3
b1 ,
b1 -
b1111 .
b0 4
b0 5
b10011 0
b101111000011110010011 %
b101111000011110010011 *
b101111000011110010011 6
b1000000000000100001000010 8
b1000001111000100000110100 7
b1000000000000000000111000 )
b1000000000000000000110100 !
b1000000000000000000110100 (
b1000000000000000000110100 +
1"
#260
0"
#270
b10111100010010 1
b101100 2
b101111 3
b1111 ,
b1111 -
b10 .
b1100 /
b1 4
b10 5
b100011 0
b10111100010010011000100011 %
b10111100010010011000100011 *
b10111100010010011000100011 6
b1000000000000000001100100 8
b1000000010010100001100110 7
b1000000000000000000111100 )
b1000000000000000000111000 !
b1000000000000000000111000 (
b1000000000000000000111000 +
1"
#280
0"
#290
b10110000010010 1
b101110 2
b101100 3
b1100 ,
b1100 -
b1110 /
b11 0
b10110000010010011100000011 %
b10110000010010011100000011 *
b10110000010010011100000011 6
b1000000000000000001101010 8
b1000000010010000001101000 7
b1000000000000000001000000 )
b1000000000000000000111100 !
b1000000000000000000111100 (
b1000000000000000000111100 +
1"
#300
0"
#310
b100100000000 1
b1111 2
b1001 3
b1001 ,
b1001 -
b0 .
b1111 /
b0 4
b0 5
b10011 0
b100100000000011110010011 %
b100100000000011110010011 *
b100100000000011110010011 6
b1000000000000100001001110 8
b1000000000000100001001000 7
b1000000000000000001000100 )
b1000000000000000001000000 !
b1000000000000000001000000 (
b1000000000000000001000000 +
1"
#320
0"
#330
b11111111111111111100111001111101 1
b11111111111111111111111111010101 2
b11111111111111111111111111001110 3
b1110 ,
b1110 -
b1111 .
b10101 /
b1111110 4
b101 5
b1100011 0
b11111100111001111101101011100011 %
b11111100111001111101101011100011 *
b11111100111001111101101011100011 6
b1000000000000000000011000 8
b111101111101100000010010 7
b1000000000000000001001000 )
b1000000000000000001000100 !
b1000000000000000001000100 (
b1000000000000000001000100 +
1"
#340
0"
#350
b10000000010010 1
b101100 2
b100000 3
b0 ,
b0 -
b10 .
b1100 /
b1 4
b10 5
b100011 0
b10000000010010011000100011 %
b10000000010010011000100011 *
b10000000010010011000100011 6
b1000000000000000001110100 8
b1000000010010000001101000 7
b1000000000000000001001100 )
b1000000000000000001001000 !
b1000000000000000001001000 (
b1000000000000000001001000 +
1"
#360
0"
#370
b11000000000000 1
b100000 2
b110000 3
b10000 ,
b10000 -
b0 .
b0 /
b0 5
b1101111 0
b11000000000000000001101111 %
b11000000000000000001101111 *
b11000000000000000001101111 6
b1000000000000000001101100 8
b1000000000000000001111100 7
b1000000000000000001010000 )
b1000000000000000001001100 !
b1000000000000000001001100 (
b1000000000000000001001100 +
1"
#380
0"
#390
b10110000010010 1
b101111 2
b101100 3
b1100 ,
b1100 -
b10 .
b1111 /
b10 5
b11 0
b10110000010010011110000011 %
b10110000010010011110000011 *
b10110000010010011110000011 6
b1000000000000100001111110 8
b1000000010010000001111100 7
b1000000000000000001010100 )
b1000000000000000001010000 !
b1000000000000000001010000 (
b1000000000000000001010000 +
1"
#400
0"
#410
b1001111001 1
b1111 2
b10 3
b10 ,
b10 -
b1111 .
b0 4
b1 5
b10011 0
b1001111001011110010011 %
b1001111001011110010011 *
b1001111001011110010011 6
b1000000000000100001100010 8
b1000001111001000001010110 7
b1000000000000000001011000 )
b1000000000000000001010100 !
b1000000000000000001010100 (
b1000000000000000001010100 +
1"
#420
0"
#430
b11000000010000 1
b101110 2
b110000 3
b10000 ,
b10000 -
b10 .
b1110 /
b1 4
b0 5
b11000000010000011100010011 %
b11000000010000011100010011 *
b11000000010000011100010011 6
b1000000000000000010000110 8
b1000000010000000010001000 7
b1000000000000000001011100 )
b1000000000000000001011000 !
b1000000000000000001011000 (
b1000000000000000001011000 +
1"
#440
0"
#450
b111101110000 1
b1111 2
b1111 3
b1111 ,
b1111 -
b1110 .
b1111 /
b0 4
b110011 0
b111101110000011110110011 %
b111101110000011110110011 *
b111101110000011110110011 6
b1000000000000100001101010 8
b1000001110000100001101010 7
b1000000000000000001100000 )
b1000000000000000001011100 !
b1000000000000000001011100 (
b1000000000000000001011100 +
1"
#460
0"
#470
b11111111111111111101000001111010 1
b11111111111111111111111111001111 2
b11111111111111111111111111010000 3
b10000 ,
b10000 -
b1111 .
b1111110 4
b10 5
b11 0
b11111101000001111010011110000011 %
b11111101000001111010011110000011 *
b11111101000001111010011110000011 6
b1000000000000000000101110 8
b111101111010100000110000 7
b1000000000000000001100100 )
b1000000000000000001100000 !
b1000000000000000001100000 (
b1000000000000000001100000 +
1"
#480
0"
#490
b10100000010010 1
b101110 2
b101000 3
b1000 ,
b1000 -
b10 .
b1110 /
b1 4
b10100000010010011100000011 %
b10100000010010011100000011 *
b10100000010010011100000011 6
b1000000000000000010010010 8
b1000000010010000010001100 7
b1000000000000000001101000 )
b1000000000000000001100100 !
b1000000000000000001100100 (
b1000000000000000001100100 +
1"
#500
0"
#510
b111101110000 1
b1111 2
b1111 3
b1111 ,
b1111 -
b1110 .
b1111 /
b0 4
b0 5
b110011 0
b111101110000011110110011 %
b111101110000011110110011 *
b111101110000011110110011 6
b1000000000000100001110110 8
b1000001110000100001110110 7
b1000000000000000001101100 )
b1000000000000000001101000 !
b1000000000000000001101000 (
b1000000000000000001101000 +
1"
#520
0"
#530
b10111100010010 1
b101000 2
b101111 3
b10 .
b1000 /
b1 4
b10 5
b100011 0
b10111100010010010000100011 %
b10111100010010010000100011 *
b10111100010010010000100011 6
b1000000000000000010010100 8
b1000000010010100010011010 7
b1000000000000000001110000 )
b1000000000000000001101100 !
b1000000000000000001101100 (
b1000000000000000001101100 +
1"
#540
0"
#550
b10110000010010 1
b101111 2
b101100 3
b1100 ,
b1100 -
b1111 /
b11 0
b10110000010010011110000011 %
b10110000010010011110000011 *
b10110000010010011110000011 6
b1000000000000100010011110 8
b1000000010010000010011100 7
b1000000000000000001110100 )
b1000000000000000001110000 !
b1000000000000000001110000 (
b1000000000000000001110000 +
1"
#560
0"
#570
b101111000 1
b1111 2
b1 3
b1 ,
b1 -
b1111 .
b0 4
b0 5
b10011 0
b101111000011110010011 %
b101111000011110010011 *
b101111000011110010011 6
b1000000000000100010000010 8
b1000001111000100001110100 7
b1000000000000000001111000 )
b1000000000000000001110100 !
b1000000000000000001110100 (
b1000000000000000001110100 +
1"
#580
0"
#590
b10111100010010 1
b101100 2
b101111 3
b1111 ,
b1111 -
b10 .
b1100 /
b1 4
b10 5
b100011 0
b10111100010010011000100011 %
b10111100010010011000100011 *
b10111100010010011000100011 6
b1000000000000000010100100 8
b1000000010010100010100110 7
b1000000000000000001111100 )
b1000000000000000001111000 !
b1000000000000000001111000 (
b1000000000000000001111000 +
1"
#600
0"
#610
b10110000010010 1
b101110 2
b101100 3
b1100 ,
b1100 -
b1110 /
b11 0
b10110000010010011100000011 %
b10110000010010011100000011 *
b10110000010010011100000011 6
b1000000000000000010101010 8
b1000000010010000010101000 7
b1000000000000000010000000 )
b1000000000000000001111100 !
b1000000000000000001111100 (
b1000000000000000001111100 +
1"
#620
0"
#630
b100100000000 1
b1111 2
b1001 3
b1001 ,
b1001 -
b0 .
b1111 /
b0 4
b0 5
b10011 0
b100100000000011110010011 %
b100100000000011110010011 *
b100100000000011110010011 6
b1000000000000100010001110 8
b1000000000000100010001000 7
b1000000000000000010000100 )
b1000000000000000010000000 !
b1000000000000000010000000 (
b1000000000000000010000000 +
1"
#640
0"
#650
b11111111111111111100111001111101 1
b11111111111111111111111111001101 2
b11111111111111111111111111001110 3
b1110 ,
b1110 -
b1111 .
b1101 /
b1111110 4
b101 5
b1100011 0
b11111100111001111101011011100011 %
b11111100111001111101011011100011 *
b11111100111001111101011011100011 6
b1000000000000000001010000 8
b111101111101100001010010 7
b1000000000000000010001000 )
b1000000000000000010000100 !
b1000000000000000010000100 (
b1000000000000000010000100 +
1"
#660
0"
#670
b10100000010010 1
b101010 2
b101000 3
b1000 ,
b1000 -
b10 .
b1010 /
b1 4
b10 5
b11 0
b10100000010010010100000011 %
b10100000010010010100000011 *
b10100000010010010100000011 6
b1000000000000000010110010 8
b1000000010010000010110000 7
b1000000000000000010001100 )
b1000000000000000010001000 !
b1000000000000000010001000 (
b1000000000000000010001000 +
1"
#680
0"
#690
b1100000000000 1
b1 2
b11000 3
b11000 ,
b11000 -
b0 .
b1 /
b0 4
b0 5
b1101111 0
b1100000000000000011101111 %
b1100000000000000011101111 *
b1100000000000000011101111 6
b1000000000000100010001100 8
b1000000000000000010100100 7
b1000000000000000010010000 )
b1000000000000000010001100 !
b1000000000000000010001100 (
b1000000000000000010001100 +
1"
#700
0"
#710
b1010000 1
b1111 2
b0 3
b0 ,
b0 -
b1010 .
b1111 /
b10011 0
b1010000011110010011 %
b1010000011110010011 *
b1010000011110010011 6
b1000000000000100010011110 8
b1000001010000000010010000 7
b1000000000000000010010100 )
b1000000000000000010010000 !
b1000000000000000010010000 (
b1000000000000000010010000 +
1"
#720
0"
#730
b1111000 1
b1010 2
b1111 .
b1010 /
b1111000010100010011 %
b1111000010100010011 *
b1111000010100010011 6
b1000000000000000010011110 8
b1000001111000000010010100 7
b1000000000000000010011000 )
b1000000000000000010010100 !
b1000000000000000010010100 (
b1000000000000000010010100 +
1"
#740
0"
#750
b11110000010010 1
b100001 2
b111100 3
b11100 ,
b11100 -
b10 .
b1 /
b1 4
b10 5
b11 0
b11110000010010000010000011 %
b11110000010010000010000011 *
b11110000010010000010000011 6
b1000000000000100010111000 8
b1000000010010000011010100 7
b1000000000000000010011100 )
b1000000000000000010011000 !
b1000000000000000010011000 (
b1000000000000000010011000 +
1"
#760
0"
#770
b100000000010000 1
b1000010 2
b1000000 3
b0 ,
b0 -
b10 /
b10 4
b0 5
b10011 0
b100000000010000000100010011 %
b100000000010000000100010011 *
b100000000010000000100010011 6
b1000000000000000011011110 8
b1000000010000000011011100 7
b1000000000000000010100000 )
b1000000000000000010011100 !
b1000000000000000010011100 (
b1000000000000000010011100 +
1"
#780
0"
#790
b1000 1
b0 2
b0 3
b1 .
b0 /
b0 4
b1100111 0
b1000000001100111 %
b1000000001100111 *
b1000000001100111 6
b1000000000000000010100000 8
b1000000001000000010100000 7
b1000000000000000010100100 )
b1000000000000000010100000 !
b1000000000000000010100000 (
b1000000000000000010100000 +
1"
#800
0"
#810
b11111111111111111110000000010000 1
b11111111111111111111111111100010 2
b11111111111111111111111111100000 3
b10 .
b10 /
b1111111 4
b10011 0
b11111110000000010000000100010011 %
b11111110000000010000000100010011 *
b11111110000000010000000100010011 6
b111111111111100010000110 8
b111100010000100010000100 7
b1000000000000000010101000 )
b1000000000000000010100100 !
b1000000000000000010100100 (
b1000000000000000010100100 +
1"
#820
0"
